[
  {
    "response" : {
      "body" : {
        "data" : {
          "signUp" : {
            "user" : {
              "email" : "fabien+test-c5eed91a-92f8-4e40-acfb-64e38afb488f@beamapp.co",
              "id" : "3ed578de-550b-4326-9202-d394c086dabc",
              "unconfirmedEmail" : null
            },
            "errors" : [

            ]
          }
        }
      },
      "status" : 200,
      "headers" : {
        "Date" : "Fri, 23 Jul 2021 10:58:06 GMT",
        "Server" : "Cowboy",
        "Via" : "1.1 vegur",
        "Connection" : "keep-alive",
        "Vary" : "Accept, Origin",
        "X-Frame-Options" : "SAMEORIGIN",
        "X-Content-Type-Options" : "nosniff",
        "Referrer-Policy" : "strict-origin-when-cross-origin",
        "Etag" : "W\/\"b7a2daea88daf3e3a6e7e17a657a93c4\"",
        "X-Runtime" : "0.276741",
        "Content-Type" : "application\/json; charset=utf-8",
        "X-Permitted-Cross-Domain-Policies" : "none",
        "X-Download-Options" : "noopen",
        "X-Xss-Protection" : "1; mode=block",
        "X-Request-Id" : "93b89595-d034-4a21-9aa8-936ffb6ba034",
        "Cache-Control" : "max-age=0, private, must-revalidate",
        "Transfer-Encoding" : "Identity",
        "Strict-Transport-Security" : "max-age=63072000; includeSubDomains"
      },
      "url" : "https:\/\/api.beamapp.co\/graphql"
    },
    "request" : {
      "url" : "https:\/\/api.beamapp.co\/graphql",
      "headers" : {
        "Content-Type" : "application\/json",
        "User-Agent" : "Beam client, 0.1.0 (1)",
        "Accept" : "application\/json",
        "Accept-Language" : "en"
      },
      "body" : {
        "query" : "mutation SignUp($email: Email!, $password: String!) {\n  signUp(input: {email: $email, password: $password}) {\n    user {\n      unconfirmedEmail\n      email\n      id\n    }\n    errors {\n      path\n      message\n    }\n  }\n}\n",
        "variables" : {
          "email" : "fabien+test-C5EED91A-92F8-4E40-ACFB-64E38AFB488F@beamapp.co",
          "password" : "MNfzfDCwYTi1"
        }
      },
      "method" : "POST"
    }
  }
]