[
  {
    "response" : {
      "url" : "https:\/\/api.beamapp.co\/graphql",
      "headers" : {
        "Cache-Control" : "max-age=0, private, must-revalidate",
        "Transfer-Encoding" : "Identity",
        "X-Frame-Options" : "SAMEORIGIN",
        "Etag" : "W\/\"2d2c0879a4bb2b5ada29a606aba9bc54\"",
        "X-Request-Id" : "27fd83f7-f90c-40e6-a021-0c5803b98086",
        "Referrer-Policy" : "strict-origin-when-cross-origin",
        "X-Permitted-Cross-Domain-Policies" : "none",
        "X-Runtime" : "0.259687",
        "Server" : "Cowboy",
        "X-Content-Type-Options" : "nosniff",
        "Content-Type" : "application\/json; charset=utf-8",
        "Connection" : "keep-alive",
        "X-Xss-Protection" : "1; mode=block",
        "Date" : "Fri, 30 Jul 2021 09:12:31 GMT",
        "Strict-Transport-Security" : "max-age=63072000; includeSubDomains",
        "X-Download-Options" : "noopen",
        "Via" : "1.1 vegur",
        "Vary" : "Accept, Origin"
      },
      "body" : {
        "data" : {
          "signUp" : {
            "user" : {
              "email" : "fabien+test-1a881ba2-41de-4f42-95fa-f3236ce18f77@beamapp.co",
              "id" : "78dee176-81b7-4d26-b84c-8f0ff4738559",
              "unconfirmedEmail" : null
            },
            "errors" : [

            ]
          }
        }
      },
      "status" : 200
    },
    "request" : {
      "body" : {
        "query" : "mutation SignUp($email: Email!, $password: String!) {\n  signUp(input: {email: $email, password: $password}) {\n    user {\n      unconfirmedEmail\n      email\n      id\n    }\n    errors {\n      path\n      message\n    }\n  }\n}\n",
        "variables" : {
          "email" : "fabien+test-1A881BA2-41DE-4F42-95FA-F3236CE18F77@beamapp.co",
          "password" : "7QPloPQ7qtKo"
        }
      },
      "url" : "https:\/\/api.beamapp.co\/graphql",
      "method" : "POST",
      "headers" : {
        "Accept-Language" : "en",
        "User-Agent" : "Beam client, 0.1.0 (1)",
        "Content-Type" : "application\/json",
        "Accept" : "application\/json"
      }
    }
  }
]