[
  {
    "response" : {
      "url" : "http:\/\/api.beam.lvh.me:5000\/graphql",
      "body" : {
        "data" : {
          "signIn" : {
            "accessToken" : "eyJhbGciOiJIUzI1NiJ9.eyJqdGkiOiJmMmJkZjM4Ni1lOTQxLTRkNmEtODY5NS03ODAxMWJkOTRlOTIiLCJzdWIiOiI4NzEwNjc5YS1jYzI2LTQxN2QtYjlkMi02ZmQ3ZjVlODM1NjgiLCJzY3AiOiJ1c2VyIiwiYXVkIjpudWxsLCJpYXQiOjE2MjgxNTUwNDMsImV4cCI6MTYzMDc4NDc4OX0.OzW0akQ8hxM_0ny1LpTxNfz32KeLfzynf5gfQj3iF-s",
            "errors" : [

            ]
          }
        }
      },
      "status" : 200,
      "headers" : {
        "X-Permitted-Cross-Domain-Policies" : "none",
        "X-Request-Id" : "5d38f467-3af5-4507-b5a4-e85a3978ca32",
        "Transfer-Encoding" : "Identity",
        "Cache-Control" : "max-age=0, private, must-revalidate",
        "Etag" : "W\/\"7e9b92c0d61d31c0880bf17f68e1508b\"",
        "X-Runtime" : "0.235974",
        "X-XSS-Protection" : "1; mode=block",
        "Vary" : "Accept, Origin",
        "X-Content-Type-Options" : "nosniff",
        "Referrer-Policy" : "strict-origin-when-cross-origin",
        "Content-Type" : "application\/json; charset=utf-8",
        "X-Download-Options" : "noopen",
        "X-Frame-Options" : "SAMEORIGIN"
      }
    },
    "request" : {
      "url" : "http:\/\/api.beam.lvh.me:5000\/graphql",
      "headers" : {
        "User-Agent" : "Beam client, 0.1.0 (1)",
        "Accept" : "application\/json",
        "Accept-Language" : "en",
        "Content-Type" : "application\/json"
      },
      "method" : "POST",
      "body" : {
        "query" : "mutation SignIn($email: Email!, $password: String!) {\n  signIn(input: {email: $email, password: $password}) {\n    accessToken\n    errors {\n      path\n      message\n    }\n  }\n}\n",
        "variables" : {
          "email" : "fabien+test@beamapp.co",
          "password" : "pict9ZUNG@mouc_vilt"
        }
      }
    }
  },
  {
    "response" : {
      "body" : {
        "data" : {
          "deleteAllDatabases" : {
            "success" : true,
            "errors" : [

            ]
          }
        }
      },
      "headers" : {
        "X-Runtime" : "0.008172",
        "X-Content-Type-Options" : "nosniff",
        "Referrer-Policy" : "strict-origin-when-cross-origin",
        "X-Download-Options" : "noopen",
        "Vary" : "Accept, Origin",
        "Etag" : "W\/\"253d6a04fc08b22a773331dc146b9a54\"",
        "X-XSS-Protection" : "1; mode=block",
        "X-Permitted-Cross-Domain-Policies" : "none",
        "X-Request-Id" : "766478e4-a03d-46c3-af08-6b42737769d6",
        "X-Frame-Options" : "SAMEORIGIN",
        "Content-Type" : "application\/json; charset=utf-8",
        "Transfer-Encoding" : "Identity",
        "Cache-Control" : "max-age=0, private, must-revalidate"
      },
      "url" : "http:\/\/api.beam.lvh.me:5000\/graphql",
      "status" : 200
    },
    "request" : {
      "method" : "POST",
      "body" : {
        "query" : "mutation DeleteAllDatabases {\n  deleteAllDatabases(input: {}) {\n    success\n    errors {\n      path\n      message\n    }\n  }\n}\n\n",
        "variables" : {

        }
      },
      "headers" : {
        "Accept" : "application\/json",
        "Accept-Language" : "en",
        "Content-Type" : "application\/json",
        "User-Agent" : "Beam client, 0.1.0 (1)",
        "Authorization" : "Bearer eyJhbGciOiJIUzI1NiJ9.eyJqdGkiOiJmMmJkZjM4Ni1lOTQxLTRkNmEtODY5NS03ODAxMWJkOTRlOTIiLCJzdWIiOiI4NzEwNjc5YS1jYzI2LTQxN2QtYjlkMi02ZmQ3ZjVlODM1NjgiLCJzY3AiOiJ1c2VyIiwiYXVkIjpudWxsLCJpYXQiOjE2MjgxNTUwNDMsImV4cCI6MTYzMDc4NDc4OX0.OzW0akQ8hxM_0ny1LpTxNfz32KeLfzynf5gfQj3iF-s"
      },
      "url" : "http:\/\/api.beam.lvh.me:5000\/graphql"
    }
  },
  {
    "response" : {
      "headers" : {
        "Vary" : "Accept, Origin",
        "Cache-Control" : "max-age=0, private, must-revalidate",
        "Etag" : "W\/\"9bba80adfb700df0be0bcaaa6095cb4e\"",
        "X-XSS-Protection" : "1; mode=block",
        "X-Runtime" : "0.008271",
        "X-Content-Type-Options" : "nosniff",
        "X-Download-Options" : "noopen",
        "X-Frame-Options" : "SAMEORIGIN",
        "Referrer-Policy" : "strict-origin-when-cross-origin",
        "X-Permitted-Cross-Domain-Policies" : "none",
        "X-Request-Id" : "9024bf1b-b86b-4182-a0ae-7b7a6f743779",
        "Content-Type" : "application\/json; charset=utf-8",
        "Transfer-Encoding" : "Identity"
      },
      "url" : "http:\/\/api.beam.lvh.me:5000\/graphql",
      "status" : 200,
      "body" : {
        "data" : {
          "deleteAllDocuments" : {
            "success" : true,
            "errors" : [

            ]
          }
        }
      }
    },
    "request" : {
      "body" : {
        "query" : "mutation DeleteAllDocuments {\n  deleteAllDocuments(input: {}) {\n    success\n    errors {\n      path\n      message\n    }\n  }\n}\n",
        "variables" : {

        }
      },
      "headers" : {
        "Authorization" : "Bearer eyJhbGciOiJIUzI1NiJ9.eyJqdGkiOiJmMmJkZjM4Ni1lOTQxLTRkNmEtODY5NS03ODAxMWJkOTRlOTIiLCJzdWIiOiI4NzEwNjc5YS1jYzI2LTQxN2QtYjlkMi02ZmQ3ZjVlODM1NjgiLCJzY3AiOiJ1c2VyIiwiYXVkIjpudWxsLCJpYXQiOjE2MjgxNTUwNDMsImV4cCI6MTYzMDc4NDc4OX0.OzW0akQ8hxM_0ny1LpTxNfz32KeLfzynf5gfQj3iF-s",
        "Content-Type" : "application\/json",
        "User-Agent" : "Beam client, 0.1.0 (1)",
        "Accept-Language" : "en",
        "Accept" : "application\/json"
      },
      "method" : "POST",
      "url" : "http:\/\/api.beam.lvh.me:5000\/graphql"
    }
  },
  {
    "request" : {
      "method" : "POST",
      "url" : "http:\/\/api.beam.lvh.me:5000\/graphql",
      "headers" : {
        "Authorization" : "Bearer eyJhbGciOiJIUzI1NiJ9.eyJqdGkiOiJmMmJkZjM4Ni1lOTQxLTRkNmEtODY5NS03ODAxMWJkOTRlOTIiLCJzdWIiOiI4NzEwNjc5YS1jYzI2LTQxN2QtYjlkMi02ZmQ3ZjVlODM1NjgiLCJzY3AiOiJ1c2VyIiwiYXVkIjpudWxsLCJpYXQiOjE2MjgxNTUwNDMsImV4cCI6MTYzMDc4NDc4OX0.OzW0akQ8hxM_0ny1LpTxNfz32KeLfzynf5gfQj3iF-s",
        "Content-Type" : "application\/json",
        "Accept-Language" : "en",
        "Accept" : "application\/json",
        "User-Agent" : "Beam client, 0.1.0 (1)"
      },
      "body" : {
        "query" : "mutation UpdateDatabase($database: DatabaseInput!) {\n  updateDatabase(input: {database: $database}) {\n    database {\n      id\n      title\n      createdAt\n      updatedAt\n      deletedAt\n    }\n    errors {\n      path\n      message\n    }\n  }\n}\n",
        "variables" : {
          "database" : {
            "id" : "995d94e1-e0df-4eca-93e6-8778984bcd29",
            "title" : "Foobar DB",
            "updatedAt" : "2021-03-19T12:21:03Z",
            "createdAt" : "2021-03-19T12:21:03Z"
          }
        }
      }
    },
    "response" : {
      "url" : "http:\/\/api.beam.lvh.me:5000\/graphql",
      "body" : {
        "data" : {
          "updateDatabase" : {
            "database" : {
              "id" : "995d94e1-e0df-4eca-93e6-8778984bcd29",
              "title" : "Foobar DB",
              "updatedAt" : "2021-03-19T12:21:03Z",
              "deletedAt" : null,
              "createdAt" : "2021-03-19T12:21:03Z"
            },
            "errors" : [

            ]
          }
        }
      },
      "status" : 200,
      "headers" : {
        "X-Request-Id" : "9f7d89b4-ff4b-4696-ba80-c091e300a6b2",
        "X-Runtime" : "0.019833",
        "X-Frame-Options" : "SAMEORIGIN",
        "Etag" : "W\/\"2769aaf65a61e83ea14eac6c93932c38\"",
        "X-Content-Type-Options" : "nosniff",
        "Vary" : "Accept, Origin",
        "Content-Type" : "application\/json; charset=utf-8",
        "X-XSS-Protection" : "1; mode=block",
        "Transfer-Encoding" : "Identity",
        "X-Permitted-Cross-Domain-Policies" : "none",
        "Cache-Control" : "max-age=0, private, must-revalidate",
        "X-Download-Options" : "noopen",
        "Referrer-Policy" : "strict-origin-when-cross-origin"
      }
    }
  },
  {
    "response" : {
      "url" : "http:\/\/api.beam.lvh.me:5000\/graphql",
      "headers" : {
        "Referrer-Policy" : "strict-origin-when-cross-origin",
        "X-Frame-Options" : "SAMEORIGIN",
        "X-Request-Id" : "bdf14e02-6be3-47e6-8aad-e184e9396e4c",
        "X-XSS-Protection" : "1; mode=block",
        "Etag" : "W\/\"8e9fdfbce7e50028b55f5f1aba80a871\"",
        "X-Permitted-Cross-Domain-Policies" : "none",
        "Cache-Control" : "max-age=0, private, must-revalidate",
        "Vary" : "Accept, Origin",
        "X-Content-Type-Options" : "nosniff",
        "X-Download-Options" : "noopen",
        "X-Runtime" : "0.014785",
        "Content-Type" : "application\/json; charset=utf-8",
        "Transfer-Encoding" : "Identity"
      },
      "body" : {
        "data" : {
          "me" : {
            "databases" : [
              {
                "id" : "995d94e1-e0df-4eca-93e6-8778984bcd29",
                "title" : "Foobar DB",
                "updatedAt" : "2021-03-19T12:21:03Z",
                "deletedAt" : null,
                "createdAt" : "2021-03-19T12:21:03Z"
              }
            ]
          }
        }
      },
      "status" : 200
    },
    "request" : {
      "headers" : {
        "Accept" : "application\/json",
        "Accept-Language" : "en",
        "Authorization" : "Bearer eyJhbGciOiJIUzI1NiJ9.eyJqdGkiOiJmMmJkZjM4Ni1lOTQxLTRkNmEtODY5NS03ODAxMWJkOTRlOTIiLCJzdWIiOiI4NzEwNjc5YS1jYzI2LTQxN2QtYjlkMi02ZmQ3ZjVlODM1NjgiLCJzY3AiOiJ1c2VyIiwiYXVkIjpudWxsLCJpYXQiOjE2MjgxNTUwNDMsImV4cCI6MTYzMDc4NDc4OX0.OzW0akQ8hxM_0ny1LpTxNfz32KeLfzynf5gfQj3iF-s",
        "User-Agent" : "Beam client, 0.1.0 (1)",
        "Content-Type" : "application\/json"
      },
      "body" : {
        "query" : "query ($updatedAtAfter: ISO8601DateTime) {\n  me {\n    databases(updatedAtAfter: $updatedAtAfter) {\n      id\n      title\n      createdAt\n      updatedAt\n      deletedAt\n    }\n  }\n}\n",
        "variables" : {

        }
      },
      "url" : "http:\/\/api.beam.lvh.me:5000\/graphql",
      "method" : "POST"
    }
  },
  {
    "response" : {
      "url" : "http:\/\/api.beam.lvh.me:5000\/graphql",
      "body" : {
        "data" : {
          "deleteDatabase" : {
            "database" : {
              "id" : "995d94e1-e0df-4eca-93e6-8778984bcd29"
            },
            "errors" : [

            ]
          }
        }
      },
      "headers" : {
        "Cache-Control" : "max-age=0, private, must-revalidate",
        "X-XSS-Protection" : "1; mode=block",
        "X-Frame-Options" : "SAMEORIGIN",
        "Etag" : "W\/\"e0bc79171e5c78c1154a1c031a89adfc\"",
        "X-Request-Id" : "ab525491-9b29-4ebd-812b-59c725b166ee",
        "Referrer-Policy" : "strict-origin-when-cross-origin",
        "Content-Type" : "application\/json; charset=utf-8",
        "Vary" : "Accept, Origin",
        "X-Content-Type-Options" : "nosniff",
        "X-Runtime" : "0.008865",
        "X-Download-Options" : "noopen",
        "X-Permitted-Cross-Domain-Policies" : "none",
        "Transfer-Encoding" : "Identity"
      },
      "status" : 200
    },
    "request" : {
      "method" : "POST",
      "body" : {
        "query" : "mutation DeleteDatabase($id: ID!) {\n  deleteDatabase(input: {database: {id: $id}}) {\n    database {\n      id\n    }\n    errors {\n      path\n      message\n    }\n  }\n}\n",
        "variables" : {
          "id" : "995d94e1-e0df-4eca-93e6-8778984bcd29"
        }
      },
      "url" : "http:\/\/api.beam.lvh.me:5000\/graphql",
      "headers" : {
        "Accept-Language" : "en",
        "User-Agent" : "Beam client, 0.1.0 (1)",
        "Content-Type" : "application\/json",
        "Authorization" : "Bearer eyJhbGciOiJIUzI1NiJ9.eyJqdGkiOiJmMmJkZjM4Ni1lOTQxLTRkNmEtODY5NS03ODAxMWJkOTRlOTIiLCJzdWIiOiI4NzEwNjc5YS1jYzI2LTQxN2QtYjlkMi02ZmQ3ZjVlODM1NjgiLCJzY3AiOiJ1c2VyIiwiYXVkIjpudWxsLCJpYXQiOjE2MjgxNTUwNDMsImV4cCI6MTYzMDc4NDc4OX0.OzW0akQ8hxM_0ny1LpTxNfz32KeLfzynf5gfQj3iF-s",
        "Accept" : "application\/json"
      }
    }
  }
]