[
  {
    "request" : {
      "url" : "https:\/\/api.beamapp.co\/graphql",
      "method" : "POST",
      "headers" : {
        "Accept" : "application\/json",
        "User-Agent" : "Beam client, 0.1.0 (1)",
        "Content-Type" : "application\/json",
        "Accept-Language" : "en"
      },
      "body" : {
        "query" : "mutation SignIn($email: Email!, $password: String!) {\n  signIn(input: {email: $email, password: $password}) {\n    accessToken\n    errors {\n      path\n      message\n    }\n  }\n}\n",
        "variables" : {
          "email" : "fabien+test@beamapp.co",
          "password" : "pict9ZUNG@mouc_vilt"
        }
      }
    },
    "response" : {
      "headers" : {
        "Strict-Transport-Security" : "max-age=63072000; includeSubDomains",
        "Cache-Control" : "max-age=0, private, must-revalidate",
        "Server" : "Cowboy",
        "X-Content-Type-Options" : "nosniff",
        "X-Request-Id" : "2581b27b-fcbb-42f3-b6d2-6f543f927c88",
        "Etag" : "W\/\"f08404102688c5f4b3957939c8e3095f\"",
        "X-Runtime" : "0.280835",
        "X-Frame-Options" : "SAMEORIGIN",
        "Connection" : "keep-alive",
        "Referrer-Policy" : "strict-origin-when-cross-origin",
        "X-Permitted-Cross-Domain-Policies" : "none",
        "Via" : "1.1 vegur",
        "X-Download-Options" : "noopen",
        "X-Xss-Protection" : "1; mode=block",
        "Vary" : "Accept, Origin",
        "Transfer-Encoding" : "Identity",
        "Content-Type" : "application\/json; charset=utf-8",
        "Date" : "Mon, 09 Aug 2021 12:08:29 GMT"
      },
      "url" : "https:\/\/api.beamapp.co\/graphql",
      "body" : {
        "data" : {
          "signIn" : {
            "accessToken" : "eyJhbGciOiJIUzI1NiJ9.eyJqdGkiOiJmZWNkMTFkMy0yZDZmLTQ3OTgtYTM4YS1lMjkzN2JmZGZmNjIiLCJzdWIiOiJlMTQwYzU5YS1lYmIyLTQ3YjEtYmU3OC05ZDJkNTYyNWRjYWQiLCJzY3AiOiJ1c2VyIiwiYXVkIjpudWxsLCJpYXQiOjE2Mjg1MTA5MTAsImV4cCI6MTYzMTE0MDY1Nn0.jtV9aBS_oywX0y4_eDcMDBjayCrqFp5tmRkC1hYcnpA",
            "errors" : [

            ]
          }
        }
      },
      "status" : 200
    }
  },
  {
    "response" : {
      "status" : 200,
      "url" : "https:\/\/api.beamapp.co\/graphql",
      "body" : {
        "data" : {
          "deleteAllDatabases" : {
            "success" : true,
            "errors" : [

            ]
          }
        }
      },
      "headers" : {
        "X-Permitted-Cross-Domain-Policies" : "none",
        "Etag" : "W\/\"253d6a04fc08b22a773331dc146b9a54\"",
        "Strict-Transport-Security" : "max-age=63072000; includeSubDomains",
        "X-Xss-Protection" : "1; mode=block",
        "X-Frame-Options" : "SAMEORIGIN",
        "Content-Type" : "application\/json; charset=utf-8",
        "Via" : "1.1 vegur",
        "X-Download-Options" : "noopen",
        "Date" : "Mon, 09 Aug 2021 12:08:30 GMT",
        "X-Request-Id" : "66d230da-6079-4de6-b45e-aa3e7e1a57e7",
        "Transfer-Encoding" : "Identity",
        "Vary" : "Accept, Origin",
        "Connection" : "keep-alive",
        "X-Runtime" : "0.011367",
        "Cache-Control" : "max-age=0, private, must-revalidate",
        "Server" : "Cowboy",
        "X-Content-Type-Options" : "nosniff",
        "Referrer-Policy" : "strict-origin-when-cross-origin"
      }
    },
    "request" : {
      "headers" : {
        "User-Agent" : "Beam client, 0.1.0 (1)",
        "Authorization" : "Bearer eyJhbGciOiJIUzI1NiJ9.eyJqdGkiOiJmZWNkMTFkMy0yZDZmLTQ3OTgtYTM4YS1lMjkzN2JmZGZmNjIiLCJzdWIiOiJlMTQwYzU5YS1lYmIyLTQ3YjEtYmU3OC05ZDJkNTYyNWRjYWQiLCJzY3AiOiJ1c2VyIiwiYXVkIjpudWxsLCJpYXQiOjE2Mjg1MTA5MTAsImV4cCI6MTYzMTE0MDY1Nn0.jtV9aBS_oywX0y4_eDcMDBjayCrqFp5tmRkC1hYcnpA",
        "Accept-Language" : "en",
        "Accept" : "application\/json",
        "Content-Type" : "application\/json"
      },
      "method" : "POST",
      "url" : "https:\/\/api.beamapp.co\/graphql",
      "body" : {
        "query" : "mutation DeleteAllDatabases {\n  deleteAllDatabases(input: {}) {\n    success\n    errors {\n      path\n      message\n    }\n  }\n}\n\n",
        "variables" : {

        }
      }
    }
  },
  {
    "request" : {
      "headers" : {
        "Accept-Language" : "en",
        "Accept" : "application\/json",
        "Authorization" : "Bearer eyJhbGciOiJIUzI1NiJ9.eyJqdGkiOiJmZWNkMTFkMy0yZDZmLTQ3OTgtYTM4YS1lMjkzN2JmZGZmNjIiLCJzdWIiOiJlMTQwYzU5YS1lYmIyLTQ3YjEtYmU3OC05ZDJkNTYyNWRjYWQiLCJzY3AiOiJ1c2VyIiwiYXVkIjpudWxsLCJpYXQiOjE2Mjg1MTA5MTAsImV4cCI6MTYzMTE0MDY1Nn0.jtV9aBS_oywX0y4_eDcMDBjayCrqFp5tmRkC1hYcnpA",
        "User-Agent" : "Beam client, 0.1.0 (1)",
        "Content-Type" : "application\/json"
      },
      "method" : "POST",
      "body" : {
        "query" : "mutation DeleteAllDocuments {\n  deleteAllDocuments(input: {}) {\n    success\n    errors {\n      path\n      message\n    }\n  }\n}\n",
        "variables" : {

        }
      },
      "url" : "https:\/\/api.beamapp.co\/graphql"
    },
    "response" : {
      "body" : {
        "data" : {
          "deleteAllDocuments" : {
            "success" : true,
            "errors" : [

            ]
          }
        }
      },
      "url" : "https:\/\/api.beamapp.co\/graphql",
      "headers" : {
        "Referrer-Policy" : "strict-origin-when-cross-origin",
        "Cache-Control" : "max-age=0, private, must-revalidate",
        "X-Download-Options" : "noopen",
        "X-Runtime" : "0.012014",
        "Connection" : "keep-alive",
        "Server" : "Cowboy",
        "X-Frame-Options" : "SAMEORIGIN",
        "X-Permitted-Cross-Domain-Policies" : "none",
        "X-Content-Type-Options" : "nosniff",
        "Content-Type" : "application\/json; charset=utf-8",
        "Date" : "Mon, 09 Aug 2021 12:08:30 GMT",
        "Transfer-Encoding" : "Identity",
        "X-Xss-Protection" : "1; mode=block",
        "Via" : "1.1 vegur",
        "Vary" : "Accept, Origin",
        "Etag" : "W\/\"9bba80adfb700df0be0bcaaa6095cb4e\"",
        "Strict-Transport-Security" : "max-age=63072000; includeSubDomains",
        "X-Request-Id" : "38fc59c8-24f3-4919-ad6f-4feb4f3f90b5"
      },
      "status" : 200
    }
  },
  {
    "response" : {
      "status" : 200,
      "body" : {
        "data" : {
          "updateDocument" : {
            "document" : {
              "id" : "995d94e1-e0df-4eca-93e6-8778984bcd18"
            },
            "errors" : [

            ]
          }
        }
      },
      "url" : "https:\/\/api.beamapp.co\/graphql",
      "headers" : {
        "X-Frame-Options" : "SAMEORIGIN",
        "Content-Type" : "application\/json; charset=utf-8",
        "Connection" : "keep-alive",
        "Date" : "Mon, 09 Aug 2021 12:08:30 GMT",
        "X-Content-Type-Options" : "nosniff",
        "Cache-Control" : "max-age=0, private, must-revalidate",
        "X-Download-Options" : "noopen",
        "Server" : "Cowboy",
        "X-Xss-Protection" : "1; mode=block",
        "Strict-Transport-Security" : "max-age=63072000; includeSubDomains",
        "X-Request-Id" : "987e5759-a1fc-4be4-8f18-48a119588b8a",
        "Etag" : "W\/\"bd1bda66157d1a6e6599bbfdbb043926\"",
        "Transfer-Encoding" : "Identity",
        "X-Runtime" : "0.047717",
        "Vary" : "Accept, Origin",
        "Referrer-Policy" : "strict-origin-when-cross-origin",
        "Via" : "1.1 vegur",
        "X-Permitted-Cross-Domain-Policies" : "none"
      }
    },
    "request" : {
      "url" : "https:\/\/api.beamapp.co\/graphql",
      "body" : {
        "query" : "mutation UpdateDocument($document: DocumentInput!) {\n  updateDocument(input: {document: $document}) {\n    document {\n      id\n    }\n    errors {\n      path\n      message\n    }\n  }\n}\n",
        "variables" : {
          "document" : {
            "id" : "995d94e1-e0df-4eca-93e6-8778984bcd18",
            "data" : "whatever binary data",
            "title" : "Fantastic Granite Car sV2hF7GoTSU2fGS9HujjWf7DqqEfD2GzzcMeQkuj",
            "documentType" : "NOTE",
            "database" : {
              "id" : "00000000-e0df-4eca-93e6-8778984bcd18",
              "title" : "Default",
              "updatedAt" : "2021-08-09T12:08:30Z",
              "createdAt" : "2021-08-09T12:08:30Z"
            },
            "updatedAt" : "2021-08-09T12:08:30Z",
            "createdAt" : "2021-08-09T12:08:30Z",
            "isPublic" : false
          }
        }
      },
      "method" : "POST",
      "headers" : {
        "Content-Type" : "application\/json",
        "Authorization" : "Bearer eyJhbGciOiJIUzI1NiJ9.eyJqdGkiOiJmZWNkMTFkMy0yZDZmLTQ3OTgtYTM4YS1lMjkzN2JmZGZmNjIiLCJzdWIiOiJlMTQwYzU5YS1lYmIyLTQ3YjEtYmU3OC05ZDJkNTYyNWRjYWQiLCJzY3AiOiJ1c2VyIiwiYXVkIjpudWxsLCJpYXQiOjE2Mjg1MTA5MTAsImV4cCI6MTYzMTE0MDY1Nn0.jtV9aBS_oywX0y4_eDcMDBjayCrqFp5tmRkC1hYcnpA",
        "Accept-Language" : "en",
        "User-Agent" : "Beam client, 0.1.0 (1)",
        "Accept" : "application\/json"
      }
    }
  },
  {
    "request" : {
      "method" : "POST",
      "headers" : {
        "Content-Type" : "application\/json",
        "Accept" : "application\/json",
        "User-Agent" : "Beam client, 0.1.0 (1)",
        "Authorization" : "Bearer eyJhbGciOiJIUzI1NiJ9.eyJqdGkiOiJmZWNkMTFkMy0yZDZmLTQ3OTgtYTM4YS1lMjkzN2JmZGZmNjIiLCJzdWIiOiJlMTQwYzU5YS1lYmIyLTQ3YjEtYmU3OC05ZDJkNTYyNWRjYWQiLCJzY3AiOiJ1c2VyIiwiYXVkIjpudWxsLCJpYXQiOjE2Mjg1MTA5MTAsImV4cCI6MTYzMTE0MDY1Nn0.jtV9aBS_oywX0y4_eDcMDBjayCrqFp5tmRkC1hYcnpA",
        "Accept-Language" : "en"
      },
      "url" : "https:\/\/api.beamapp.co\/graphql",
      "body" : {
        "query" : "query document($id: ID!) {\n  document(id: $id) {\n    id\n    title\n    slug\n    data\n    createdAt\n    updatedAt\n    deletedAt\n    isPublic\n    database { title id }\n    documentType\n    publicUrl\n  }\n}\n",
        "variables" : {
          "id" : "995d94e1-e0df-4eca-93e6-8778984bcd18"
        }
      }
    },
    "response" : {
      "headers" : {
        "X-Download-Options" : "noopen",
        "Server" : "Cowboy",
        "Connection" : "keep-alive",
        "Vary" : "Accept, Origin",
        "Transfer-Encoding" : "Identity",
        "X-Runtime" : "0.010531",
        "Referrer-Policy" : "strict-origin-when-cross-origin",
        "X-Request-Id" : "63f373d4-89d1-44cf-bfbe-fbd795883019",
        "X-Content-Type-Options" : "nosniff",
        "X-Permitted-Cross-Domain-Policies" : "none",
        "Etag" : "W\/\"2111a16abf6c989e6fffa164e0dfb1a0\"",
        "Date" : "Mon, 09 Aug 2021 12:08:30 GMT",
        "X-Frame-Options" : "SAMEORIGIN",
        "Strict-Transport-Security" : "max-age=63072000; includeSubDomains",
        "Cache-Control" : "max-age=0, private, must-revalidate",
        "Via" : "1.1 vegur",
        "Content-Type" : "application\/json; charset=utf-8",
        "X-Xss-Protection" : "1; mode=block"
      },
      "url" : "https:\/\/api.beamapp.co\/graphql",
      "status" : 200,
      "body" : {
        "data" : {
          "document" : {
            "slug" : "fantastic-granite-car-sv2hf7gotsu2fgs9hujjwf7dqqefd2gzzcmeqkuj",
            "id" : "995d94e1-e0df-4eca-93e6-8778984bcd18",
            "data" : "whatever binary data",
            "title" : "Fantastic Granite Car sV2hF7GoTSU2fGS9HujjWf7DqqEfD2GzzcMeQkuj",
            "deletedAt" : null,
            "database" : {
              "title" : "Default",
              "id" : "00000000-e0df-4eca-93e6-8778984bcd18"
            },
            "updatedAt" : "2021-08-09T12:08:30Z",
            "createdAt" : "2021-08-09T12:08:30Z",
            "isPublic" : false,
            "documentType" : "NOTE",
            "publicUrl" : "https:\/\/app.beamapp.co\/documents\/ce384312-03ae-4fd2-9ac7-d53265960193"
          }
        }
      }
    }
  },
  {
    "response" : {
      "url" : "https:\/\/api.beamapp.co\/graphql",
      "body" : {
        "data" : {
          "updateDocument" : {
            "document" : {
              "id" : "995d94e1-e0df-4eca-93e6-8778984bcd18"
            },
            "errors" : [

            ]
          }
        }
      },
      "status" : 200,
      "headers" : {
        "Connection" : "keep-alive",
        "X-Content-Type-Options" : "nosniff",
        "Server" : "Cowboy",
        "Etag" : "W\/\"bd1bda66157d1a6e6599bbfdbb043926\"",
        "Via" : "1.1 vegur",
        "X-Runtime" : "0.041312",
        "Referrer-Policy" : "strict-origin-when-cross-origin",
        "X-Frame-Options" : "SAMEORIGIN",
        "Date" : "Mon, 09 Aug 2021 12:08:30 GMT",
        "X-Permitted-Cross-Domain-Policies" : "none",
        "Vary" : "Accept, Origin",
        "X-Xss-Protection" : "1; mode=block",
        "Strict-Transport-Security" : "max-age=63072000; includeSubDomains",
        "X-Request-Id" : "3d99d417-0823-4461-972b-bc540f71a3be",
        "Cache-Control" : "max-age=0, private, must-revalidate",
        "Transfer-Encoding" : "Identity",
        "X-Download-Options" : "noopen",
        "Content-Type" : "application\/json; charset=utf-8"
      }
    },
    "request" : {
      "headers" : {
        "Authorization" : "Bearer eyJhbGciOiJIUzI1NiJ9.eyJqdGkiOiJmZWNkMTFkMy0yZDZmLTQ3OTgtYTM4YS1lMjkzN2JmZGZmNjIiLCJzdWIiOiJlMTQwYzU5YS1lYmIyLTQ3YjEtYmU3OC05ZDJkNTYyNWRjYWQiLCJzY3AiOiJ1c2VyIiwiYXVkIjpudWxsLCJpYXQiOjE2Mjg1MTA5MTAsImV4cCI6MTYzMTE0MDY1Nn0.jtV9aBS_oywX0y4_eDcMDBjayCrqFp5tmRkC1hYcnpA",
        "Content-Type" : "application\/json",
        "Accept" : "application\/json",
        "User-Agent" : "Beam client, 0.1.0 (1)",
        "Accept-Language" : "en"
      },
      "url" : "https:\/\/api.beamapp.co\/graphql",
      "method" : "POST",
      "body" : {
        "query" : "mutation UpdateDocument($document: DocumentInput!) {\n  updateDocument(input: {document: $document}) {\n    document {\n      id\n    }\n    errors {\n      path\n      message\n    }\n  }\n}\n",
        "variables" : {
          "document" : {
            "id" : "995d94e1-e0df-4eca-93e6-8778984bcd18",
            "data" : "whatever binary data",
            "title" : "Fantastic Granite Car sV2hF7GoTSU2fGS9HujjWf7DqqEfD2GzzcMeQkuj",
            "documentType" : "NOTE",
            "database" : {
              "id" : "11111111-e0df-4eca-93e6-8778984bcd18",
              "title" : "Foobar DB",
              "updatedAt" : "2021-08-09T12:08:30Z",
              "createdAt" : "2021-08-09T12:08:30Z"
            },
            "updatedAt" : "2021-08-09T12:08:30Z",
            "createdAt" : "2021-08-09T12:08:30Z",
            "isPublic" : false
          }
        }
      }
    }
  },
  {
    "request" : {
      "method" : "POST",
      "headers" : {
        "User-Agent" : "Beam client, 0.1.0 (1)",
        "Accept" : "application\/json",
        "Content-Type" : "application\/json",
        "Accept-Language" : "en",
        "Authorization" : "Bearer eyJhbGciOiJIUzI1NiJ9.eyJqdGkiOiJmZWNkMTFkMy0yZDZmLTQ3OTgtYTM4YS1lMjkzN2JmZGZmNjIiLCJzdWIiOiJlMTQwYzU5YS1lYmIyLTQ3YjEtYmU3OC05ZDJkNTYyNWRjYWQiLCJzY3AiOiJ1c2VyIiwiYXVkIjpudWxsLCJpYXQiOjE2Mjg1MTA5MTAsImV4cCI6MTYzMTE0MDY1Nn0.jtV9aBS_oywX0y4_eDcMDBjayCrqFp5tmRkC1hYcnpA"
      },
      "body" : {
        "query" : "query document($id: ID!) {\n  document(id: $id) {\n    id\n    title\n    slug\n    data\n    createdAt\n    updatedAt\n    deletedAt\n    isPublic\n    database { title id }\n    documentType\n    publicUrl\n  }\n}\n",
        "variables" : {
          "id" : "995d94e1-e0df-4eca-93e6-8778984bcd18"
        }
      },
      "url" : "https:\/\/api.beamapp.co\/graphql"
    },
    "response" : {
      "url" : "https:\/\/api.beamapp.co\/graphql",
      "headers" : {
        "X-Runtime" : "0.013977",
        "Server" : "Cowboy",
        "Via" : "1.1 vegur",
        "X-Content-Type-Options" : "nosniff",
        "X-Download-Options" : "noopen",
        "Vary" : "Accept, Origin",
        "Connection" : "keep-alive",
        "Transfer-Encoding" : "Identity",
        "X-Xss-Protection" : "1; mode=block",
        "Referrer-Policy" : "strict-origin-when-cross-origin",
        "Etag" : "W\/\"f72ae85e47b4b3ebdf56955b7914cc70\"",
        "X-Permitted-Cross-Domain-Policies" : "none",
        "X-Request-Id" : "39892a4b-d66e-4038-b887-848977255b0b",
        "Date" : "Mon, 09 Aug 2021 12:08:30 GMT",
        "Cache-Control" : "max-age=0, private, must-revalidate",
        "X-Frame-Options" : "SAMEORIGIN",
        "Content-Type" : "application\/json; charset=utf-8",
        "Strict-Transport-Security" : "max-age=63072000; includeSubDomains"
      },
      "status" : 200,
      "body" : {
        "data" : {
          "document" : {
            "slug" : "fantastic-granite-car-sv2hf7gotsu2fgs9hujjwf7dqqefd2gzzcmeqkuj",
            "id" : "995d94e1-e0df-4eca-93e6-8778984bcd18",
            "data" : "whatever binary data",
            "title" : "Fantastic Granite Car sV2hF7GoTSU2fGS9HujjWf7DqqEfD2GzzcMeQkuj",
            "deletedAt" : null,
            "database" : {
              "title" : "Foobar DB",
              "id" : "11111111-e0df-4eca-93e6-8778984bcd18"
            },
            "updatedAt" : "2021-08-09T12:08:30Z",
            "createdAt" : "2021-08-09T12:08:30Z",
            "isPublic" : false,
            "documentType" : "NOTE",
            "publicUrl" : "https:\/\/app.beamapp.co\/documents\/ce384312-03ae-4fd2-9ac7-d53265960193"
          }
        }
      }
    }
  },
  {
    "request" : {
      "method" : "POST",
      "headers" : {
        "Content-Type" : "application\/json",
        "User-Agent" : "Beam client, 0.1.0 (1)",
        "Accept-Language" : "en",
        "Accept" : "application\/json",
        "Authorization" : "Bearer eyJhbGciOiJIUzI1NiJ9.eyJqdGkiOiJmZWNkMTFkMy0yZDZmLTQ3OTgtYTM4YS1lMjkzN2JmZGZmNjIiLCJzdWIiOiJlMTQwYzU5YS1lYmIyLTQ3YjEtYmU3OC05ZDJkNTYyNWRjYWQiLCJzY3AiOiJ1c2VyIiwiYXVkIjpudWxsLCJpYXQiOjE2Mjg1MTA5MTAsImV4cCI6MTYzMTE0MDY1Nn0.jtV9aBS_oywX0y4_eDcMDBjayCrqFp5tmRkC1hYcnpA"
      },
      "body" : {
        "query" : "mutation DeleteDocument($id: ID!) {\n  deleteDocument(input: {document: {id: $id}}) {\n    document {\n      id\n    }\n    errors {\n      path\n      message\n    }\n  }\n}\n",
        "variables" : {
          "id" : "995d94e1-e0df-4eca-93e6-8778984bcd18"
        }
      },
      "url" : "https:\/\/api.beamapp.co\/graphql"
    },
    "response" : {
      "body" : {
        "data" : {
          "deleteDocument" : {
            "document" : {
              "id" : "995d94e1-e0df-4eca-93e6-8778984bcd18"
            },
            "errors" : [

            ]
          }
        }
      },
      "status" : 200,
      "headers" : {
        "X-Frame-Options" : "SAMEORIGIN",
        "Referrer-Policy" : "strict-origin-when-cross-origin",
        "Connection" : "keep-alive",
        "X-Permitted-Cross-Domain-Policies" : "none",
        "Date" : "Mon, 09 Aug 2021 12:08:30 GMT",
        "Server" : "Cowboy",
        "Via" : "1.1 vegur",
        "X-Request-Id" : "1209b538-8fcf-4054-bf5d-0274980b7ea2",
        "X-Download-Options" : "noopen",
        "Cache-Control" : "max-age=0, private, must-revalidate",
        "Transfer-Encoding" : "Identity",
        "X-Content-Type-Options" : "nosniff",
        "Strict-Transport-Security" : "max-age=63072000; includeSubDomains",
        "X-Xss-Protection" : "1; mode=block",
        "Etag" : "W\/\"276bf2cfd4e3cd57c640f9fb108817a7\"",
        "Content-Type" : "application\/json; charset=utf-8",
        "X-Runtime" : "0.024579",
        "Vary" : "Accept, Origin"
      },
      "url" : "https:\/\/api.beamapp.co\/graphql"
    }
  }
]