[
  {
    "request" : {
      "body" : {
        "query" : "mutation SignIn($email: Email!, $password: String!) {\n  signIn(input: {email: $email, password: $password}) {\n    accessToken\n    errors {\n      path\n      message\n    }\n  }\n}\n",
        "variables" : {
          "email" : "fabien+test@beamapp.co",
          "password" : "pict9ZUNG@mouc_vilt"
        }
      },
      "method" : "POST",
      "headers" : {
        "User-Agent" : "Beam client, 0.1.0 (1)",
        "Accept" : "application\/json",
        "Content-Type" : "application\/json",
        "Accept-Language" : "en"
      },
      "url" : "http:\/\/api.beam.lvh.me:5000\/graphql"
    },
    "response" : {
      "body" : {
        "data" : {
          "signIn" : {
            "accessToken" : "eyJhbGciOiJIUzI1NiJ9.eyJqdGkiOiJmMmJkZjM4Ni1lOTQxLTRkNmEtODY5NS03ODAxMWJkOTRlOTIiLCJzdWIiOiI4NzEwNjc5YS1jYzI2LTQxN2QtYjlkMi02ZmQ3ZjVlODM1NjgiLCJzY3AiOiJ1c2VyIiwiYXVkIjpudWxsLCJpYXQiOjE2MjgxNTUxMTcsImV4cCI6MTYzMDc4NDg2M30.tAoPF646tDjH6grzsOFYJ0_hJz6hmohV4SRRpQ81E6M",
            "errors" : [

            ]
          }
        }
      },
      "url" : "http:\/\/api.beam.lvh.me:5000\/graphql",
      "headers" : {
        "X-Download-Options" : "noopen",
        "Cache-Control" : "max-age=0, private, must-revalidate",
        "Etag" : "W\/\"76d0caa08dee9b0070dd10d1d924be02\"",
        "X-Runtime" : "0.234898",
        "X-Request-Id" : "91cd7ef8-00dc-4286-8936-fdf2ac274301",
        "X-Content-Type-Options" : "nosniff",
        "X-Permitted-Cross-Domain-Policies" : "none",
        "Referrer-Policy" : "strict-origin-when-cross-origin",
        "Content-Type" : "application\/json; charset=utf-8",
        "X-XSS-Protection" : "1; mode=block",
        "Transfer-Encoding" : "Identity",
        "Vary" : "Accept, Origin",
        "X-Frame-Options" : "SAMEORIGIN"
      },
      "status" : 200
    }
  },
  {
    "request" : {
      "body" : {
        "query" : "mutation UpdateBeamObject($beamObject: BeamObjectInput!, $privateKey: String) {\n  updateBeamObject(input: {beamObject: $beamObject, privateKey: $privateKey}) {\n    beamObject {\n      id\n      checksum\n      type\n    }\n    errors {\n      objectid\n      path\n      message\n    }\n  }\n}\n",
        "variables" : {
          "beamObject" : {
            "id" : "195D94E1-E0DF-4ECA-93E6-8778984BCD58",
            "data" : "8plTjSY68dF9NkLWM+tp\/yMQcadt9V6j2ES1le7u5aODh38DlmlY6eUYSUnyDfpko\/F9AtuP\/7uHz0rtPXLSSZ1Cnh0UyW27QAhUiAozw9+Z4lg71zssYOh4cifpcxmSjfE4mksNrgz0ILWDmSFfwIsGRYJcCguI",
            "checksum" : "1329717e2a5c440af3e94efeecba3bee495963998506bb662c0ab2da0cd459e6",
            "privateKeySignature" : "45cb7cb283d0b9ca64219bd0bc033c0fad461aaf6783d5be71eac2e772c3c828",
            "updatedAt" : "2021-03-19T12:21:03Z",
            "type" : "my_remote_object",
            "createdAt" : "2021-03-19T12:21:03Z"
          },
          "privateKey" : "j6tifPZTjUtGoz+1RJkO8dOMlu48MUUSlwACw\/fCBw0="
        }
      },
      "method" : "POST",
      "headers" : {
        "Accept" : "application\/json",
        "User-Agent" : "Beam client, 0.1.0 (1)",
        "Authorization" : "Bearer eyJhbGciOiJIUzI1NiJ9.eyJqdGkiOiJmMmJkZjM4Ni1lOTQxLTRkNmEtODY5NS03ODAxMWJkOTRlOTIiLCJzdWIiOiI4NzEwNjc5YS1jYzI2LTQxN2QtYjlkMi02ZmQ3ZjVlODM1NjgiLCJzY3AiOiJ1c2VyIiwiYXVkIjpudWxsLCJpYXQiOjE2MjgxNTUxMTcsImV4cCI6MTYzMDc4NDg2M30.tAoPF646tDjH6grzsOFYJ0_hJz6hmohV4SRRpQ81E6M",
        "Content-Type" : "application\/json",
        "Accept-Language" : "en"
      },
      "url" : "http:\/\/api.beam.lvh.me:5000\/graphql"
    },
    "response" : {
      "body" : {
        "data" : {
          "updateBeamObject" : {
            "beamObject" : {
              "id" : "195d94e1-e0df-4eca-93e6-8778984bcd58",
              "checksum" : "1329717e2a5c440af3e94efeecba3bee495963998506bb662c0ab2da0cd459e6",
              "type" : "my_remote_object"
            },
            "errors" : [

            ]
          }
        }
      },
      "headers" : {
        "X-Runtime" : "0.023994",
        "X-Frame-Options" : "SAMEORIGIN",
        "Cache-Control" : "max-age=0, private, must-revalidate",
        "Content-Type" : "application\/json; charset=utf-8",
        "X-Content-Type-Options" : "nosniff",
        "Referrer-Policy" : "strict-origin-when-cross-origin",
        "Etag" : "W\/\"a8a311b2628b8bf3e25297188328faf1\"",
        "X-Permitted-Cross-Domain-Policies" : "none",
        "X-Download-Options" : "noopen",
        "X-XSS-Protection" : "1; mode=block",
        "Transfer-Encoding" : "Identity",
        "Vary" : "Accept, Origin",
        "X-Request-Id" : "0370ef1f-113f-4371-8ac4-22abe32039e7"
      },
      "url" : "http:\/\/api.beam.lvh.me:5000\/graphql",
      "status" : 200
    }
  },
  {
    "request" : {
      "body" : {
        "query" : "mutation UpdateBeamObject($beamObject: BeamObjectInput!, $privateKey: String) {\n  updateBeamObject(input: {beamObject: $beamObject, privateKey: $privateKey}) {\n    beamObject {\n      id\n      checksum\n      type\n    }\n    errors {\n      objectid\n      path\n      message\n    }\n  }\n}\n",
        "variables" : {
          "beamObject" : {
            "id" : "295D94E1-E0DF-4ECA-93E6-8778984BCD58",
            "data" : "pvZr+SdUwfgQ2Kjr2UJwaNi1dg1PiKz0nxVYhrS\/OKPAu5DppURJWQP+ZNz74jfXjd1klVqfS4v4DJUlPsloKMDN21\/m+Ggsepn7hI6Fghjxn+W\/mnlup3UCoUalt6dgtq1kimNH0QigweCNxJ9s\/JCSsiKqNZQN",
            "checksum" : "dbc369736dade41722b7005db5efae1fb99aca7aae9417b6184eaf423e2d860b",
            "privateKeySignature" : "45cb7cb283d0b9ca64219bd0bc033c0fad461aaf6783d5be71eac2e772c3c828",
            "updatedAt" : "2021-03-19T12:21:03Z",
            "type" : "my_remote_object",
            "createdAt" : "2021-03-19T12:21:03Z"
          },
          "privateKey" : "j6tifPZTjUtGoz+1RJkO8dOMlu48MUUSlwACw\/fCBw0="
        }
      },
      "method" : "POST",
      "url" : "http:\/\/api.beam.lvh.me:5000\/graphql",
      "headers" : {
        "User-Agent" : "Beam client, 0.1.0 (1)",
        "Accept" : "application\/json",
        "Content-Type" : "application\/json",
        "Accept-Language" : "en",
        "Authorization" : "Bearer eyJhbGciOiJIUzI1NiJ9.eyJqdGkiOiJmMmJkZjM4Ni1lOTQxLTRkNmEtODY5NS03ODAxMWJkOTRlOTIiLCJzdWIiOiI4NzEwNjc5YS1jYzI2LTQxN2QtYjlkMi02ZmQ3ZjVlODM1NjgiLCJzY3AiOiJ1c2VyIiwiYXVkIjpudWxsLCJpYXQiOjE2MjgxNTUxMTcsImV4cCI6MTYzMDc4NDg2M30.tAoPF646tDjH6grzsOFYJ0_hJz6hmohV4SRRpQ81E6M"
      }
    },
    "response" : {
      "url" : "http:\/\/api.beam.lvh.me:5000\/graphql",
      "headers" : {
        "X-Permitted-Cross-Domain-Policies" : "none",
        "Cache-Control" : "max-age=0, private, must-revalidate",
        "X-Download-Options" : "noopen",
        "X-Frame-Options" : "SAMEORIGIN",
        "X-Content-Type-Options" : "nosniff",
        "X-Request-Id" : "71dbe03f-6e5d-48ef-85ac-b9f8454b4721",
        "X-Runtime" : "0.023075",
        "Content-Type" : "application\/json; charset=utf-8",
        "Transfer-Encoding" : "Identity",
        "Vary" : "Accept, Origin",
        "X-XSS-Protection" : "1; mode=block",
        "Etag" : "W\/\"2100926b6305b0ca2eb4150b0db75563\"",
        "Referrer-Policy" : "strict-origin-when-cross-origin"
      },
      "body" : {
        "data" : {
          "updateBeamObject" : {
            "beamObject" : {
              "id" : "295d94e1-e0df-4eca-93e6-8778984bcd58",
              "checksum" : "dbc369736dade41722b7005db5efae1fb99aca7aae9417b6184eaf423e2d860b",
              "type" : "my_remote_object"
            },
            "errors" : [

            ]
          }
        }
      },
      "status" : 200
    }
  },
  {
    "request" : {
      "body" : {
        "query" : "mutation UpdateBeamObject($beamObject: BeamObjectInput!, $privateKey: String) {\n  updateBeamObject(input: {beamObject: $beamObject, privateKey: $privateKey}) {\n    beamObject {\n      id\n      checksum\n      type\n    }\n    errors {\n      objectid\n      path\n      message\n    }\n  }\n}\n",
        "variables" : {
          "beamObject" : {
            "id" : "395D94E1-E0DF-4ECA-93E6-8778984BCD58",
            "data" : "102CoF5yeHaWp\/h3ocCXylbjeLyfrfEHpURw3lS00Un8xJHwOvB3EPqpwbaZQSuHQPGWfWI4sqALyIm8Clw\/hN0G0BWTxMTYQ8F\/4v3HtvlMMzaeEXcxydfl6VWh\/kHzTGGe\/rekuIVJN38RI+IqpU9+Q7ut+0Lr",
            "checksum" : "fe147aac80e027967f9dae92fc5d272bd0c06519b18f7b27d1aa7feb2a4e3d3f",
            "privateKeySignature" : "45cb7cb283d0b9ca64219bd0bc033c0fad461aaf6783d5be71eac2e772c3c828",
            "updatedAt" : "2021-03-19T12:21:03Z",
            "type" : "my_remote_object",
            "createdAt" : "2021-03-19T12:21:03Z"
          },
          "privateKey" : "j6tifPZTjUtGoz+1RJkO8dOMlu48MUUSlwACw\/fCBw0="
        }
      },
      "url" : "http:\/\/api.beam.lvh.me:5000\/graphql",
      "headers" : {
        "Content-Type" : "application\/json",
        "Accept-Language" : "en",
        "Authorization" : "Bearer eyJhbGciOiJIUzI1NiJ9.eyJqdGkiOiJmMmJkZjM4Ni1lOTQxLTRkNmEtODY5NS03ODAxMWJkOTRlOTIiLCJzdWIiOiI4NzEwNjc5YS1jYzI2LTQxN2QtYjlkMi02ZmQ3ZjVlODM1NjgiLCJzY3AiOiJ1c2VyIiwiYXVkIjpudWxsLCJpYXQiOjE2MjgxNTUxMTcsImV4cCI6MTYzMDc4NDg2M30.tAoPF646tDjH6grzsOFYJ0_hJz6hmohV4SRRpQ81E6M",
        "User-Agent" : "Beam client, 0.1.0 (1)",
        "Accept" : "application\/json"
      },
      "method" : "POST"
    },
    "response" : {
      "body" : {
        "data" : {
          "updateBeamObject" : {
            "beamObject" : {
              "id" : "395d94e1-e0df-4eca-93e6-8778984bcd58",
              "checksum" : "fe147aac80e027967f9dae92fc5d272bd0c06519b18f7b27d1aa7feb2a4e3d3f",
              "type" : "my_remote_object"
            },
            "errors" : [

            ]
          }
        }
      },
      "url" : "http:\/\/api.beam.lvh.me:5000\/graphql",
      "status" : 200,
      "headers" : {
        "X-Permitted-Cross-Domain-Policies" : "none",
        "Referrer-Policy" : "strict-origin-when-cross-origin",
        "X-XSS-Protection" : "1; mode=block",
        "Etag" : "W\/\"cd5231149cee0fb2dc2c1125957f91a8\"",
        "Transfer-Encoding" : "Identity",
        "Vary" : "Accept, Origin",
        "X-Content-Type-Options" : "nosniff",
        "X-Request-Id" : "71bc3c51-3158-4549-baaa-ecac619d76b2",
        "X-Download-Options" : "noopen",
        "Cache-Control" : "max-age=0, private, must-revalidate",
        "Content-Type" : "application\/json; charset=utf-8",
        "X-Frame-Options" : "SAMEORIGIN",
        "X-Runtime" : "0.015373"
      }
    }
  },
  {
    "request" : {
      "method" : "POST",
      "headers" : {
        "Accept-Language" : "en",
        "Authorization" : "Bearer eyJhbGciOiJIUzI1NiJ9.eyJqdGkiOiJmMmJkZjM4Ni1lOTQxLTRkNmEtODY5NS03ODAxMWJkOTRlOTIiLCJzdWIiOiI4NzEwNjc5YS1jYzI2LTQxN2QtYjlkMi02ZmQ3ZjVlODM1NjgiLCJzY3AiOiJ1c2VyIiwiYXVkIjpudWxsLCJpYXQiOjE2MjgxNTUxMTcsImV4cCI6MTYzMDc4NDg2M30.tAoPF646tDjH6grzsOFYJ0_hJz6hmohV4SRRpQ81E6M",
        "Accept" : "application\/json",
        "Content-Type" : "application\/json",
        "User-Agent" : "Beam client, 0.1.0 (1)"
      },
      "url" : "http:\/\/api.beam.lvh.me:5000\/graphql",
      "body" : {
        "query" : "mutation UpdateBeamObjects($beamObjects: [BeamObjectInput!]!, $privateKey: String) {\n  updateBeamObjects(input: {beamObjectsInput: $beamObjects, privateKey: $privateKey}) {\n    beamObjects {\n      id\n      checksum\n      type\n    }\n    errors {\n      objectid\n      path\n      message\n    }\n  }\n}\n",
        "variables" : {
          "privateKey" : "j6tifPZTjUtGoz+1RJkO8dOMlu48MUUSlwACw\/fCBw0=",
          "beamObjects" : [
            {
              "id" : "195D94E1-E0DF-4ECA-93E6-8778984BCD58",
              "data" : "vzEfrbKsZ7iTRrud6oGojnEZMImVrTOeoKHO9KRF0v4xsr5tu5WxsjbrQvySYlbcWdQtvn1OXNd9aPGD38LpjPCdKll0tk89eekMNLNQiTzDOaQa87LII4z8\/uuiBGb4D0M\/yTHEYlcgbTKhianBXNZqBqf3Y64AtiA=",
              "checksum" : "6bd6950a479d12bbd7ca9824b570b15510803b24f0667b275a6c9be7b46ab0b9",
              "previousChecksum" : "00a3c318664ebae8b2239cd2be6dae3f546feb789cb005fa9f31512709f2fb00",
              "privateKeySignature" : "45cb7cb283d0b9ca64219bd0bc033c0fad461aaf6783d5be71eac2e772c3c828",
              "updatedAt" : "2021-03-19T12:21:03Z",
              "type" : "my_remote_object",
              "createdAt" : "2021-03-19T12:21:03Z"
            },
            {
              "id" : "295D94E1-E0DF-4ECA-93E6-8778984BCD58",
              "data" : "J4hmI2n2jyHz2X6AXjr3NJW5UmsE5mpbb+hHxrxIErpmw6UPnoD0Kcrs3b9vyLDmPiLtW+RLKgsYtXHc7+gjh1ZTQ+adKi8yV+nJAR5XTkvJAvsJBfsfiodBL\/V8FHmEsZunMuyKJYC2mbkMzfbEVgRQUbeLZTMTrB4=",
              "checksum" : "30be1cf47851e3baa34f1c06b2ded0f683e84284962b46bcd1a8a166449c9c8c",
              "previousChecksum" : "11a3c318664ebae8b2239cd2be6dae3f546feb789cb005fa9f31512709f2fb11",
              "privateKeySignature" : "45cb7cb283d0b9ca64219bd0bc033c0fad461aaf6783d5be71eac2e772c3c828",
              "updatedAt" : "2021-03-19T12:21:03Z",
              "type" : "my_remote_object",
              "createdAt" : "2021-03-19T12:21:03Z"
            },
            {
              "id" : "395D94E1-E0DF-4ECA-93E6-8778984BCD58",
              "data" : "OJW7wO+65k3k0HirDHlkUufS2ICkn0bhmg6odQjTdSauQ+XZt9Mlxz9EuzsovT5H2QhCYXCYdUE6U9JY5+AulG39Im9q5I+QPpP6bu9zPzkHZ0yxmgkom+MSQ40jBRZdVR6f1Ed2xvnvVs\/Wt5x7zHysezcwiuHf",
              "checksum" : "fe147aac80e027967f9dae92fc5d272bd0c06519b18f7b27d1aa7feb2a4e3d3f",
              "previousChecksum" : "fe147aac80e027967f9dae92fc5d272bd0c06519b18f7b27d1aa7feb2a4e3d3f",
              "privateKeySignature" : "45cb7cb283d0b9ca64219bd0bc033c0fad461aaf6783d5be71eac2e772c3c828",
              "updatedAt" : "2021-03-19T12:21:03Z",
              "type" : "my_remote_object",
              "createdAt" : "2021-03-19T12:21:03Z"
            }
          ]
        }
      }
    },
    "response" : {
      "url" : "http:\/\/api.beam.lvh.me:5000\/graphql",
      "body" : {
        "data" : {
          "updateBeamObjects" : {
            "errors" : [
              {
                "path" : [
                  "attributes",
                  "previous_checksum"
                ],
                "objectid" : "195d94e1-e0df-4eca-93e6-8778984bcd58",
                "message" : "Differs from current checksum"
              },
              {
                "path" : [
                  "attributes",
                  "previous_checksum"
                ],
                "objectid" : "295d94e1-e0df-4eca-93e6-8778984bcd58",
                "message" : "Differs from current checksum"
              }
            ],
            "beamObjects" : [
              {
                "id" : "395d94e1-e0df-4eca-93e6-8778984bcd58",
                "checksum" : "fe147aac80e027967f9dae92fc5d272bd0c06519b18f7b27d1aa7feb2a4e3d3f",
                "type" : "my_remote_object"
              }
            ]
          }
        }
      },
      "status" : 200,
      "headers" : {
        "X-Runtime" : "0.021125",
        "Content-Type" : "application\/json; charset=utf-8",
        "X-Download-Options" : "noopen",
        "X-XSS-Protection" : "1; mode=block",
        "X-Frame-Options" : "SAMEORIGIN",
        "Referrer-Policy" : "strict-origin-when-cross-origin",
        "Vary" : "Accept, Origin",
        "Transfer-Encoding" : "Identity",
        "X-Permitted-Cross-Domain-Policies" : "none",
        "X-Content-Type-Options" : "nosniff",
        "X-Request-Id" : "bab5b5bc-bbeb-4104-bf6e-13fea0f0ca95",
        "Etag" : "W\/\"497f8d347c15491cfc149492fec4df84\"",
        "Cache-Control" : "max-age=0, private, must-revalidate"
      }
    }
  },
  {
    "response" : {
      "status" : 200,
      "headers" : {
        "Cache-Control" : "max-age=0, private, must-revalidate",
        "X-Permitted-Cross-Domain-Policies" : "none",
        "X-Content-Type-Options" : "nosniff",
        "Transfer-Encoding" : "Identity",
        "Referrer-Policy" : "strict-origin-when-cross-origin",
        "X-Runtime" : "0.010070",
        "Vary" : "Accept, Origin",
        "Content-Type" : "application\/json; charset=utf-8",
        "X-Request-Id" : "26d3e82a-6b4c-46aa-a65f-fe71e2b71498",
        "Etag" : "W\/\"565d3296d34d49d995da44c34fa5229e\"",
        "X-Frame-Options" : "SAMEORIGIN",
        "X-Download-Options" : "noopen",
        "X-XSS-Protection" : "1; mode=block"
      },
      "url" : "http:\/\/api.beam.lvh.me:5000\/graphql",
      "body" : {
        "data" : {
          "beamObject" : {
            "id" : "195d94e1-e0df-4eca-93e6-8778984bcd58",
            "data" : "8plTjSY68dF9NkLWM+tp\/yMQcadt9V6j2ES1le7u5aODh38DlmlY6eUYSUnyDfpko\/F9AtuP\/7uHz0rtPXLSSZ1Cnh0UyW27QAhUiAozw9+Z4lg71zssYOh4cifpcxmSjfE4mksNrgz0ILWDmSFfwIsGRYJcCguI",
            "checksum" : "1329717e2a5c440af3e94efeecba3bee495963998506bb662c0ab2da0cd459e6",
            "deletedAt" : null,
            "updatedAt" : "2021-03-19T12:21:03Z",
            "type" : "my_remote_object",
            "createdAt" : "2021-03-19T12:21:03Z"
          }
        }
      }
    },
    "request" : {
      "url" : "http:\/\/api.beam.lvh.me:5000\/graphql",
      "method" : "POST",
      "body" : {
        "query" : "query beamObject($id: ID!) {\n  beamObject(id: $id) {\n    id\n    data\n    checksum\n    type\n    createdAt\n    updatedAt\n    deletedAt\n  }\n}\n",
        "variables" : {
          "id" : "195D94E1-E0DF-4ECA-93E6-8778984BCD58"
        }
      },
      "headers" : {
        "Content-Type" : "application\/json",
        "Accept" : "application\/json",
        "Accept-Language" : "en",
        "Authorization" : "Bearer eyJhbGciOiJIUzI1NiJ9.eyJqdGkiOiJmMmJkZjM4Ni1lOTQxLTRkNmEtODY5NS03ODAxMWJkOTRlOTIiLCJzdWIiOiI4NzEwNjc5YS1jYzI2LTQxN2QtYjlkMi02ZmQ3ZjVlODM1NjgiLCJzY3AiOiJ1c2VyIiwiYXVkIjpudWxsLCJpYXQiOjE2MjgxNTUxMTcsImV4cCI6MTYzMDc4NDg2M30.tAoPF646tDjH6grzsOFYJ0_hJz6hmohV4SRRpQ81E6M",
        "User-Agent" : "Beam client, 0.1.0 (1)"
      }
    }
  },
  {
    "request" : {
      "headers" : {
        "Accept-Language" : "en",
        "Content-Type" : "application\/json",
        "Accept" : "application\/json",
        "User-Agent" : "Beam client, 0.1.0 (1)",
        "Authorization" : "Bearer eyJhbGciOiJIUzI1NiJ9.eyJqdGkiOiJmMmJkZjM4Ni1lOTQxLTRkNmEtODY5NS03ODAxMWJkOTRlOTIiLCJzdWIiOiI4NzEwNjc5YS1jYzI2LTQxN2QtYjlkMi02ZmQ3ZjVlODM1NjgiLCJzY3AiOiJ1c2VyIiwiYXVkIjpudWxsLCJpYXQiOjE2MjgxNTUxMTcsImV4cCI6MTYzMDc4NDg2M30.tAoPF646tDjH6grzsOFYJ0_hJz6hmohV4SRRpQ81E6M"
      },
      "method" : "POST",
      "url" : "http:\/\/api.beam.lvh.me:5000\/graphql",
      "body" : {
        "query" : "query beamObject($id: ID!) {\n  beamObject(id: $id) {\n    id\n    data\n    checksum\n    type\n    createdAt\n    updatedAt\n    deletedAt\n  }\n}\n",
        "variables" : {
          "id" : "295D94E1-E0DF-4ECA-93E6-8778984BCD58"
        }
      }
    },
    "response" : {
      "status" : 200,
      "headers" : {
        "Etag" : "W\/\"2909f894392e86c42e78dbc2b2f8be6b\"",
        "X-Runtime" : "0.009991",
        "X-Permitted-Cross-Domain-Policies" : "none",
        "X-Frame-Options" : "SAMEORIGIN",
        "Cache-Control" : "max-age=0, private, must-revalidate",
        "X-XSS-Protection" : "1; mode=block",
        "X-Download-Options" : "noopen",
        "Transfer-Encoding" : "Identity",
        "X-Content-Type-Options" : "nosniff",
        "Referrer-Policy" : "strict-origin-when-cross-origin",
        "Vary" : "Accept, Origin",
        "X-Request-Id" : "538930a4-49f6-424a-920d-d64aa7180b4d",
        "Content-Type" : "application\/json; charset=utf-8"
      },
      "url" : "http:\/\/api.beam.lvh.me:5000\/graphql",
      "body" : {
        "data" : {
          "beamObject" : {
            "id" : "295d94e1-e0df-4eca-93e6-8778984bcd58",
            "data" : "pvZr+SdUwfgQ2Kjr2UJwaNi1dg1PiKz0nxVYhrS\/OKPAu5DppURJWQP+ZNz74jfXjd1klVqfS4v4DJUlPsloKMDN21\/m+Ggsepn7hI6Fghjxn+W\/mnlup3UCoUalt6dgtq1kimNH0QigweCNxJ9s\/JCSsiKqNZQN",
            "checksum" : "dbc369736dade41722b7005db5efae1fb99aca7aae9417b6184eaf423e2d860b",
            "deletedAt" : null,
            "updatedAt" : "2021-03-19T12:21:03Z",
            "type" : "my_remote_object",
            "createdAt" : "2021-03-19T12:21:03Z"
          }
        }
      }
    }
  },
  {
    "request" : {
      "url" : "http:\/\/api.beam.lvh.me:5000\/graphql",
      "method" : "POST",
      "body" : {
        "query" : "mutation UpdateBeamObjects($beamObjects: [BeamObjectInput!]!, $privateKey: String) {\n  updateBeamObjects(input: {beamObjectsInput: $beamObjects, privateKey: $privateKey}) {\n    beamObjects {\n      id\n      checksum\n      type\n    }\n    errors {\n      objectid\n      path\n      message\n    }\n  }\n}\n",
        "variables" : {
          "privateKey" : "j6tifPZTjUtGoz+1RJkO8dOMlu48MUUSlwACw\/fCBw0=",
          "beamObjects" : [
            {
              "id" : "195D94E1-E0DF-4ECA-93E6-8778984BCD58",
              "data" : "EZOuZW9BhSxcBSVJlLhvQqFoMIjKKhof21YQmn+zfMUxqYcJSJPLNysLr7+qAiVcYm637Wb4T0EjFX41vjoI2jz9Qt+jqEDd52wdfYBkp\/RUtnbWuk7Fw1OKpEiYPsWVZtmI5bIamKtyEpuW1uwPquDqewCB+QY3zQ8a1dr8GHy30KIPsm0fjtJJ",
              "checksum" : "f4cd6499ffbd657bd7649afb6ba8a7777c7fd225fe906d471edd60bff246f595",
              "previousChecksum" : "1329717e2a5c440af3e94efeecba3bee495963998506bb662c0ab2da0cd459e6",
              "privateKeySignature" : "45cb7cb283d0b9ca64219bd0bc033c0fad461aaf6783d5be71eac2e772c3c828",
              "updatedAt" : "2021-03-19T12:21:03Z",
              "type" : "my_remote_object",
              "createdAt" : "2021-03-19T12:21:03Z"
            },
            {
              "id" : "295D94E1-E0DF-4ECA-93E6-8778984BCD58",
              "data" : "lRcB6m8uZzM23HRnvqDebgiKczWbYxjktQVYw6E05M5uGHj4Zj6Rt0q80oFnJ02wZ1c1uJb5XrH7LeEDMypdGPURfWTL1EXkX83U1ENt8lzAkR\/L6dSGZq2KMh3Loiu2+xvLPKkaQlPJfmkXucegN9DPqqiEtRJIIBFf2I0P28W3qawRCBO+6\/Hf",
              "checksum" : "c74c22e7ebcb927ca666ff2ec5b9ab68ab6bd19c6f4a735236de58004d646230",
              "previousChecksum" : "dbc369736dade41722b7005db5efae1fb99aca7aae9417b6184eaf423e2d860b",
              "privateKeySignature" : "45cb7cb283d0b9ca64219bd0bc033c0fad461aaf6783d5be71eac2e772c3c828",
              "updatedAt" : "2021-03-19T12:21:03Z",
              "type" : "my_remote_object",
              "createdAt" : "2021-03-19T12:21:03Z"
            }
          ]
        }
      },
      "headers" : {
        "Accept" : "application\/json",
        "Content-Type" : "application\/json",
        "User-Agent" : "Beam client, 0.1.0 (1)",
        "Authorization" : "Bearer eyJhbGciOiJIUzI1NiJ9.eyJqdGkiOiJmMmJkZjM4Ni1lOTQxLTRkNmEtODY5NS03ODAxMWJkOTRlOTIiLCJzdWIiOiI4NzEwNjc5YS1jYzI2LTQxN2QtYjlkMi02ZmQ3ZjVlODM1NjgiLCJzY3AiOiJ1c2VyIiwiYXVkIjpudWxsLCJpYXQiOjE2MjgxNTUxMTcsImV4cCI6MTYzMDc4NDg2M30.tAoPF646tDjH6grzsOFYJ0_hJz6hmohV4SRRpQ81E6M",
        "Accept-Language" : "en"
      }
    },
    "response" : {
      "status" : 200,
      "body" : {
        "data" : {
          "updateBeamObjects" : {
            "errors" : [

            ],
            "beamObjects" : [
              {
                "id" : "195d94e1-e0df-4eca-93e6-8778984bcd58",
                "checksum" : "f4cd6499ffbd657bd7649afb6ba8a7777c7fd225fe906d471edd60bff246f595",
                "type" : "my_remote_object"
              },
              {
                "id" : "295d94e1-e0df-4eca-93e6-8778984bcd58",
                "checksum" : "c74c22e7ebcb927ca666ff2ec5b9ab68ab6bd19c6f4a735236de58004d646230",
                "type" : "my_remote_object"
              }
            ]
          }
        }
      },
      "url" : "http:\/\/api.beam.lvh.me:5000\/graphql",
      "headers" : {
        "X-Runtime" : "0.014669",
        "Transfer-Encoding" : "Identity",
        "X-Permitted-Cross-Domain-Policies" : "none",
        "Vary" : "Accept, Origin",
        "Etag" : "W\/\"66fea39f380727afce42676c8d4090f1\"",
        "X-Request-Id" : "3cf19127-5a91-48a9-805e-b3b9952b8cd2",
        "Cache-Control" : "max-age=0, private, must-revalidate",
        "X-Download-Options" : "noopen",
        "X-Content-Type-Options" : "nosniff",
        "X-Frame-Options" : "SAMEORIGIN",
        "X-XSS-Protection" : "1; mode=block",
        "Content-Type" : "application\/json; charset=utf-8",
        "Referrer-Policy" : "strict-origin-when-cross-origin"
      }
    }
  },
  {
    "response" : {
      "headers" : {
        "X-Content-Type-Options" : "nosniff",
        "X-Runtime" : "0.005568",
        "Etag" : "W\/\"4979b027853222033b78668c613a2e60\"",
        "Cache-Control" : "max-age=0, private, must-revalidate",
        "X-XSS-Protection" : "1; mode=block",
        "X-Permitted-Cross-Domain-Policies" : "none",
        "X-Download-Options" : "noopen",
        "Transfer-Encoding" : "Identity",
        "Referrer-Policy" : "strict-origin-when-cross-origin",
        "Vary" : "Accept, Origin",
        "X-Frame-Options" : "SAMEORIGIN",
        "X-Request-Id" : "2f07cdb9-135c-40c0-98ec-990f5f629560",
        "Content-Type" : "application\/json; charset=utf-8"
      },
      "body" : {
        "data" : {
          "deleteAllBeamObjects" : {
            "success" : true,
            "errors" : [

            ]
          }
        }
      },
      "url" : "http:\/\/api.beam.lvh.me:5000\/graphql",
      "status" : 200
    },
    "request" : {
      "method" : "POST",
      "url" : "http:\/\/api.beam.lvh.me:5000\/graphql",
      "headers" : {
        "User-Agent" : "Beam client, 0.1.0 (1)",
        "Authorization" : "Bearer eyJhbGciOiJIUzI1NiJ9.eyJqdGkiOiJmMmJkZjM4Ni1lOTQxLTRkNmEtODY5NS03ODAxMWJkOTRlOTIiLCJzdWIiOiI4NzEwNjc5YS1jYzI2LTQxN2QtYjlkMi02ZmQ3ZjVlODM1NjgiLCJzY3AiOiJ1c2VyIiwiYXVkIjpudWxsLCJpYXQiOjE2MjgxNTUxMTcsImV4cCI6MTYzMDc4NDg2M30.tAoPF646tDjH6grzsOFYJ0_hJz6hmohV4SRRpQ81E6M",
        "Content-Type" : "application\/json",
        "Accept" : "application\/json",
        "Accept-Language" : "en"
      },
      "body" : {
        "query" : "mutation DeleteAllBeamObjects {\n  deleteAllBeamObjects(input: {}) {\n    success\n    errors {\n      path\n      message\n    }\n  }\n}\n",
        "variables" : {

        }
      }
    }
  }
]