[
  {
    "request" : {
      "body" : {
        "query" : "mutation SignIn($email: Email!, $password: String!) {\n  signIn(input: {email: $email, password: $password}) {\n    accessToken\n    errors {\n      path\n      message\n    }\n  }\n}\n",
        "variables" : {
          "email" : "fabien+test@beamapp.co",
          "password" : "pict9ZUNG@mouc_vilt"
        }
      },
      "url" : "https:\/\/api.beamapp.co\/graphql",
      "headers" : {
        "Accept-Language" : "en",
        "User-Agent" : "Beam client, 0.1.0 (1)",
        "Accept" : "application\/json",
        "Content-Type" : "application\/json"
      },
      "method" : "POST"
    },
    "response" : {
      "headers" : {
        "Connection" : "keep-alive",
        "Strict-Transport-Security" : "max-age=63072000; includeSubDomains",
        "Transfer-Encoding" : "Identity",
        "X-Download-Options" : "noopen",
        "X-Xss-Protection" : "1; mode=block",
        "X-Runtime" : "0.256292",
        "Date" : "Wed, 04 Aug 2021 15:04:43 GMT",
        "X-Permitted-Cross-Domain-Policies" : "none",
        "Vary" : "Accept, Origin",
        "Server" : "Cowboy",
        "Content-Type" : "application\/json; charset=utf-8",
        "X-Request-Id" : "40330cd2-44e0-4948-befd-6a55f7c96c13",
        "Via" : "1.1 vegur",
        "Referrer-Policy" : "strict-origin-when-cross-origin",
        "Cache-Control" : "max-age=0, private, must-revalidate",
        "X-Frame-Options" : "SAMEORIGIN",
        "X-Content-Type-Options" : "nosniff",
        "Etag" : "W\/\"62b46c5fb8d6c3436dc4cadc57ea8d57\""
      },
      "url" : "https:\/\/api.beamapp.co\/graphql",
      "body" : {
        "data" : {
          "signIn" : {
            "accessToken" : "eyJhbGciOiJIUzI1NiJ9.eyJqdGkiOiJmZWNkMTFkMy0yZDZmLTQ3OTgtYTM4YS1lMjkzN2JmZGZmNjIiLCJzdWIiOiJlMTQwYzU5YS1lYmIyLTQ3YjEtYmU3OC05ZDJkNTYyNWRjYWQiLCJzY3AiOiJ1c2VyIiwiYXVkIjpudWxsLCJpYXQiOjE2MjgwODk0ODMsImV4cCI6MTYzMDcxOTIyOX0.bOoRmXwT_12k7ztxWbzOpLLMhaVoLXKW9nD4-i7B1qU",
            "errors" : [

            ]
          }
        }
      },
      "status" : 200
    }
  },
  {
    "request" : {
      "headers" : {
        "User-Agent" : "Beam client, 0.1.0 (1)",
        "Accept-Language" : "en",
        "Accept" : "application\/json",
        "Content-Type" : "application\/json",
        "Authorization" : "Bearer eyJhbGciOiJIUzI1NiJ9.eyJqdGkiOiJmZWNkMTFkMy0yZDZmLTQ3OTgtYTM4YS1lMjkzN2JmZGZmNjIiLCJzdWIiOiJlMTQwYzU5YS1lYmIyLTQ3YjEtYmU3OC05ZDJkNTYyNWRjYWQiLCJzY3AiOiJ1c2VyIiwiYXVkIjpudWxsLCJpYXQiOjE2MjgwODk0ODMsImV4cCI6MTYzMDcxOTIyOX0.bOoRmXwT_12k7ztxWbzOpLLMhaVoLXKW9nD4-i7B1qU"
      },
      "url" : "https:\/\/api.beamapp.co\/graphql",
      "body" : {
        "query" : "mutation UpdateBeamObject($beamObject: BeamObjectInput!, $privateKey: String) {\n  updateBeamObject(input: {beamObject: $beamObject, privateKey: $privateKey}) {\n    beamObject {\n      id\n      checksum\n      type\n    }\n    errors {\n      objectid\n      path\n      message\n    }\n  }\n}\n",
        "variables" : {
          "beamObject" : {
            "id" : "195D94E1-E0DF-4ECA-93E6-8778984BCD58",
            "data" : "{\"data\":\"pDq23qh0IrHaAXJM9UtoaPJ1rOZdmscR23m8U0\\\/ihQzSJ8r5WGHJaiCwyi2wSCenRcYRdwLHyZ7y9hDpOXnp3OujWnk63tYjlcEdSsRXRscp8qMwMCxjVzMjW0zuJzPm\\\/5mPMKH3DsEnhwuAURd0qipr+b4pPJGn\",\"encryptionName\":\"AES_GCM\",\"privateKeySha256\":\"45cb7cb283d0b9ca64219bd0bc033c0fad461aaf6783d5be71eac2e772c3c828\"}",
            "updatedAt" : "2021-03-19T12:21:03Z",
            "type" : "my_remote_object",
            "checksum" : "1329717e2a5c440af3e94efeecba3bee495963998506bb662c0ab2da0cd459e6",
            "createdAt" : "2021-03-19T12:21:03Z"
          },
          "privateKey" : "j6tifPZTjUtGoz+1RJkO8dOMlu48MUUSlwACw\/fCBw0="
        }
      },
      "method" : "POST"
    },
    "response" : {
      "headers" : {
        "Connection" : "keep-alive",
        "Cache-Control" : "max-age=0, private, must-revalidate",
        "Etag" : "W\/\"a8a311b2628b8bf3e25297188328faf1\"",
        "Date" : "Wed, 04 Aug 2021 15:04:43 GMT",
        "X-Runtime" : "0.026769",
        "Referrer-Policy" : "strict-origin-when-cross-origin",
        "Transfer-Encoding" : "Identity",
        "X-Xss-Protection" : "1; mode=block",
        "X-Request-Id" : "ef6188fd-2b85-4d44-a847-62b52db012bd",
        "X-Permitted-Cross-Domain-Policies" : "none",
        "Vary" : "Accept, Origin",
        "X-Frame-Options" : "SAMEORIGIN",
        "X-Download-Options" : "noopen",
        "Via" : "1.1 vegur",
        "X-Content-Type-Options" : "nosniff",
        "Server" : "Cowboy",
        "Content-Type" : "application\/json; charset=utf-8",
        "Strict-Transport-Security" : "max-age=63072000; includeSubDomains"
      },
      "url" : "https:\/\/api.beamapp.co\/graphql",
      "status" : 200,
      "body" : {
        "data" : {
          "updateBeamObject" : {
            "beamObject" : {
              "id" : "195d94e1-e0df-4eca-93e6-8778984bcd58",
              "checksum" : "1329717e2a5c440af3e94efeecba3bee495963998506bb662c0ab2da0cd459e6",
              "type" : "my_remote_object"
            },
            "errors" : [

            ]
          }
        }
      }
    }
  },
  {
    "request" : {
      "headers" : {
        "Accept-Language" : "en",
        "User-Agent" : "Beam client, 0.1.0 (1)",
        "Authorization" : "Bearer eyJhbGciOiJIUzI1NiJ9.eyJqdGkiOiJmZWNkMTFkMy0yZDZmLTQ3OTgtYTM4YS1lMjkzN2JmZGZmNjIiLCJzdWIiOiJlMTQwYzU5YS1lYmIyLTQ3YjEtYmU3OC05ZDJkNTYyNWRjYWQiLCJzY3AiOiJ1c2VyIiwiYXVkIjpudWxsLCJpYXQiOjE2MjgwODk0ODMsImV4cCI6MTYzMDcxOTIyOX0.bOoRmXwT_12k7ztxWbzOpLLMhaVoLXKW9nD4-i7B1qU",
        "Accept" : "application\/json",
        "Content-Type" : "application\/json"
      },
      "url" : "https:\/\/api.beamapp.co\/graphql",
      "body" : {
        "query" : "query beamObject($id: ID!) {\n  beamObject(id: $id) {\n    id\n    data\n    checksum\n    type\n    createdAt\n    updatedAt\n    deletedAt\n  }\n}\n",
        "variables" : {
          "id" : "195D94E1-E0DF-4ECA-93E6-8778984BCD58"
        }
      },
      "method" : "POST"
    },
    "response" : {
      "url" : "https:\/\/api.beamapp.co\/graphql",
      "headers" : {
        "Etag" : "W\/\"ff3c66dbfef73f4e3e66422b8996749e\"",
        "Connection" : "keep-alive",
        "X-Permitted-Cross-Domain-Policies" : "none",
        "X-Runtime" : "0.010150",
        "X-Frame-Options" : "SAMEORIGIN",
        "Cache-Control" : "max-age=0, private, must-revalidate",
        "Content-Type" : "application\/json; charset=utf-8",
        "Server" : "Cowboy",
        "Date" : "Wed, 04 Aug 2021 15:04:43 GMT",
        "Referrer-Policy" : "strict-origin-when-cross-origin",
        "X-Download-Options" : "noopen",
        "Transfer-Encoding" : "Identity",
        "X-Content-Type-Options" : "nosniff",
        "X-Xss-Protection" : "1; mode=block",
        "Via" : "1.1 vegur",
        "Vary" : "Accept, Origin",
        "Strict-Transport-Security" : "max-age=63072000; includeSubDomains",
        "X-Request-Id" : "e56303b9-5746-46c3-b4ad-a6367de6084f"
      },
      "status" : 200,
      "body" : {
        "data" : {
          "beamObject" : {
            "id" : "195d94e1-e0df-4eca-93e6-8778984bcd58",
            "data" : "{\"data\":\"pDq23qh0IrHaAXJM9UtoaPJ1rOZdmscR23m8U0\\\/ihQzSJ8r5WGHJaiCwyi2wSCenRcYRdwLHyZ7y9hDpOXnp3OujWnk63tYjlcEdSsRXRscp8qMwMCxjVzMjW0zuJzPm\\\/5mPMKH3DsEnhwuAURd0qipr+b4pPJGn\",\"encryptionName\":\"AES_GCM\",\"privateKeySha256\":\"45cb7cb283d0b9ca64219bd0bc033c0fad461aaf6783d5be71eac2e772c3c828\"}",
            "checksum" : "1329717e2a5c440af3e94efeecba3bee495963998506bb662c0ab2da0cd459e6",
            "deletedAt" : null,
            "updatedAt" : "2021-03-19T12:21:03Z",
            "type" : "my_remote_object",
            "createdAt" : "2021-03-19T12:21:03Z"
          }
        }
      }
    }
  },
  {
    "request" : {
      "method" : "POST",
      "body" : {
        "query" : "mutation DeleteAllBeamObjects {\n  deleteAllBeamObjects(input: {}) {\n    success\n    errors {\n      path\n      message\n    }\n  }\n}\n",
        "variables" : {

        }
      },
      "url" : "https:\/\/api.beamapp.co\/graphql",
      "headers" : {
        "Authorization" : "Bearer eyJhbGciOiJIUzI1NiJ9.eyJqdGkiOiJmZWNkMTFkMy0yZDZmLTQ3OTgtYTM4YS1lMjkzN2JmZGZmNjIiLCJzdWIiOiJlMTQwYzU5YS1lYmIyLTQ3YjEtYmU3OC05ZDJkNTYyNWRjYWQiLCJzY3AiOiJ1c2VyIiwiYXVkIjpudWxsLCJpYXQiOjE2MjgwODk0ODMsImV4cCI6MTYzMDcxOTIyOX0.bOoRmXwT_12k7ztxWbzOpLLMhaVoLXKW9nD4-i7B1qU",
        "Accept-Language" : "en",
        "Content-Type" : "application\/json",
        "Accept" : "application\/json",
        "User-Agent" : "Beam client, 0.1.0 (1)"
      }
    },
    "response" : {
      "body" : {
        "data" : {
          "deleteAllBeamObjects" : {
            "success" : true,
            "errors" : [

            ]
          }
        }
      },
      "status" : 200,
      "url" : "https:\/\/api.beamapp.co\/graphql",
      "headers" : {
        "X-Download-Options" : "noopen",
        "X-Content-Type-Options" : "nosniff",
        "X-Xss-Protection" : "1; mode=block",
        "Server" : "Cowboy",
        "Date" : "Wed, 04 Aug 2021 15:04:43 GMT",
        "Referrer-Policy" : "strict-origin-when-cross-origin",
        "Cache-Control" : "max-age=0, private, must-revalidate",
        "Via" : "1.1 vegur",
        "Etag" : "W\/\"4979b027853222033b78668c613a2e60\"",
        "Content-Type" : "application\/json; charset=utf-8",
        "X-Runtime" : "0.010959",
        "X-Permitted-Cross-Domain-Policies" : "none",
        "Transfer-Encoding" : "Identity",
        "Connection" : "keep-alive",
        "Strict-Transport-Security" : "max-age=63072000; includeSubDomains",
        "X-Frame-Options" : "SAMEORIGIN",
        "Vary" : "Accept, Origin",
        "X-Request-Id" : "f9a85c92-e43c-4ee5-bd0b-c3f4b3bd4d9e"
      }
    }
  }
]