[
  {
    "request" : {
      "body" : {
        "query" : "mutation SignIn($email: Email!, $password: String!) {\n  signIn(input: {email: $email, password: $password}) {\n    accessToken\n    errors {\n      path\n      message\n    }\n  }\n}\n",
        "variables" : {
          "email" : "fabien+test@beamapp.co",
          "password" : "pict9ZUNG@mouc_vilt"
        }
      },
      "url" : "https:\/\/api.beamapp.co\/graphql",
      "method" : "POST",
      "headers" : {
        "Accept" : "application\/json",
        "Accept-Language" : "en",
        "Content-Type" : "application\/json",
        "User-Agent" : "Beam client, 0.1.0 (1)"
      }
    },
    "response" : {
      "body" : {
        "data" : {
          "signIn" : {
            "accessToken" : "eyJhbGciOiJIUzI1NiJ9.eyJqdGkiOiJmZWNkMTFkMy0yZDZmLTQ3OTgtYTM4YS1lMjkzN2JmZGZmNjIiLCJzdWIiOiJlMTQwYzU5YS1lYmIyLTQ3YjEtYmU3OC05ZDJkNTYyNWRjYWQiLCJzY3AiOiJ1c2VyIiwiYXVkIjpudWxsLCJpYXQiOjE2MjgwODk0NzgsImV4cCI6MTYzMDcxOTIyNH0.9b3qmS4IWHbQ1R2nQ_YLe_s58bMP_iegQXcLAJC7w-I",
            "errors" : [

            ]
          }
        }
      },
      "status" : 200,
      "url" : "https:\/\/api.beamapp.co\/graphql",
      "headers" : {
        "X-Frame-Options" : "SAMEORIGIN",
        "Cache-Control" : "max-age=0, private, must-revalidate",
        "Content-Type" : "application\/json; charset=utf-8",
        "Connection" : "keep-alive",
        "Vary" : "Accept, Origin",
        "X-Content-Type-Options" : "nosniff",
        "X-Xss-Protection" : "1; mode=block",
        "Strict-Transport-Security" : "max-age=63072000; includeSubDomains",
        "Transfer-Encoding" : "Identity",
        "Referrer-Policy" : "strict-origin-when-cross-origin",
        "X-Permitted-Cross-Domain-Policies" : "none",
        "Via" : "1.1 vegur",
        "Date" : "Wed, 04 Aug 2021 15:04:37 GMT",
        "X-Runtime" : "0.254597",
        "X-Request-Id" : "ef3b5f32-2b68-43db-8e79-cf7ff5077479",
        "X-Download-Options" : "noopen",
        "Etag" : "W\/\"1579f56757decbf44018805f6eb301db\"",
        "Server" : "Cowboy"
      }
    }
  },
  {
    "request" : {
      "url" : "https:\/\/api.beamapp.co\/graphql",
      "body" : {
        "query" : "mutation UpdateBeamObject($beamObject: BeamObjectInput!, $privateKey: String) {\n  updateBeamObject(input: {beamObject: $beamObject, privateKey: $privateKey}) {\n    beamObject {\n      id\n      checksum\n      type\n    }\n    errors {\n      objectid\n      path\n      message\n    }\n  }\n}\n",
        "variables" : {
          "beamObject" : {
            "id" : "195D94E1-E0DF-4ECA-93E6-8778984BCD58",
            "data" : "{\"data\":\"RdFjSZMkQh0yDja9mtlnUAwn3X2kWBKybvvDX01imisAkEHtAldrWYoIIWn2RI6eXjHWdturL9\\\/4EcSZPN5cqda2c1I20KxW\\\/kmT4dURvWJsr4L4x\\\/+4B94RD4eZjzSTRBSMbz3xfGOrddrfLef4ppSXoMybN6Hl\",\"encryptionName\":\"AES_GCM\",\"privateKeySha256\":\"45cb7cb283d0b9ca64219bd0bc033c0fad461aaf6783d5be71eac2e772c3c828\"}",
            "updatedAt" : "2021-03-19T12:21:03Z",
            "type" : "my_remote_object",
            "checksum" : "1329717e2a5c440af3e94efeecba3bee495963998506bb662c0ab2da0cd459e6",
            "createdAt" : "2021-03-19T12:21:03Z"
          },
          "privateKey" : "j6tifPZTjUtGoz+1RJkO8dOMlu48MUUSlwACw\/fCBw0="
        }
      },
      "headers" : {
        "Authorization" : "Bearer eyJhbGciOiJIUzI1NiJ9.eyJqdGkiOiJmZWNkMTFkMy0yZDZmLTQ3OTgtYTM4YS1lMjkzN2JmZGZmNjIiLCJzdWIiOiJlMTQwYzU5YS1lYmIyLTQ3YjEtYmU3OC05ZDJkNTYyNWRjYWQiLCJzY3AiOiJ1c2VyIiwiYXVkIjpudWxsLCJpYXQiOjE2MjgwODk0NzgsImV4cCI6MTYzMDcxOTIyNH0.9b3qmS4IWHbQ1R2nQ_YLe_s58bMP_iegQXcLAJC7w-I",
        "Accept-Language" : "en",
        "Content-Type" : "application\/json",
        "User-Agent" : "Beam client, 0.1.0 (1)",
        "Accept" : "application\/json"
      },
      "method" : "POST"
    },
    "response" : {
      "url" : "https:\/\/api.beamapp.co\/graphql",
      "status" : 200,
      "body" : {
        "data" : {
          "updateBeamObject" : {
            "beamObject" : {
              "id" : "195d94e1-e0df-4eca-93e6-8778984bcd58",
              "checksum" : "1329717e2a5c440af3e94efeecba3bee495963998506bb662c0ab2da0cd459e6",
              "type" : "my_remote_object"
            },
            "errors" : [

            ]
          }
        }
      },
      "headers" : {
        "X-Xss-Protection" : "1; mode=block",
        "Connection" : "keep-alive",
        "Transfer-Encoding" : "Identity",
        "X-Request-Id" : "6653e2a8-3853-4150-8dee-58152d1e3066",
        "X-Permitted-Cross-Domain-Policies" : "none",
        "Cache-Control" : "max-age=0, private, must-revalidate",
        "X-Runtime" : "0.026514",
        "Date" : "Wed, 04 Aug 2021 15:04:37 GMT",
        "X-Content-Type-Options" : "nosniff",
        "Content-Type" : "application\/json; charset=utf-8",
        "Via" : "1.1 vegur",
        "X-Frame-Options" : "SAMEORIGIN",
        "Referrer-Policy" : "strict-origin-when-cross-origin",
        "Vary" : "Accept, Origin",
        "Strict-Transport-Security" : "max-age=63072000; includeSubDomains",
        "Etag" : "W\/\"a8a311b2628b8bf3e25297188328faf1\"",
        "Server" : "Cowboy",
        "X-Download-Options" : "noopen"
      }
    }
  },
  {
    "response" : {
      "url" : "https:\/\/api.beamapp.co\/graphql",
      "body" : {
        "data" : {
          "updateBeamObject" : {
            "beamObject" : {
              "id" : "295d94e1-e0df-4eca-93e6-8778984bcd58",
              "checksum" : "dbc369736dade41722b7005db5efae1fb99aca7aae9417b6184eaf423e2d860b",
              "type" : "my_remote_object"
            },
            "errors" : [

            ]
          }
        }
      },
      "headers" : {
        "X-Request-Id" : "94c8e8fa-5e9b-49ad-bd6d-bfc5d532e5d0",
        "Content-Type" : "application\/json; charset=utf-8",
        "Strict-Transport-Security" : "max-age=63072000; includeSubDomains",
        "Date" : "Wed, 04 Aug 2021 15:04:37 GMT",
        "Transfer-Encoding" : "Identity",
        "X-Permitted-Cross-Domain-Policies" : "none",
        "Server" : "Cowboy",
        "X-Runtime" : "0.031815",
        "Connection" : "keep-alive",
        "X-Frame-Options" : "SAMEORIGIN",
        "Cache-Control" : "max-age=0, private, must-revalidate",
        "Vary" : "Accept, Origin",
        "X-Xss-Protection" : "1; mode=block",
        "X-Download-Options" : "noopen",
        "Referrer-Policy" : "strict-origin-when-cross-origin",
        "Etag" : "W\/\"2100926b6305b0ca2eb4150b0db75563\"",
        "Via" : "1.1 vegur",
        "X-Content-Type-Options" : "nosniff"
      },
      "status" : 200
    },
    "request" : {
      "method" : "POST",
      "body" : {
        "query" : "mutation UpdateBeamObject($beamObject: BeamObjectInput!, $privateKey: String) {\n  updateBeamObject(input: {beamObject: $beamObject, privateKey: $privateKey}) {\n    beamObject {\n      id\n      checksum\n      type\n    }\n    errors {\n      objectid\n      path\n      message\n    }\n  }\n}\n",
        "variables" : {
          "beamObject" : {
            "id" : "295D94E1-E0DF-4ECA-93E6-8778984BCD58",
            "data" : "{\"data\":\"KqBQuzKH9gq+ahGqrsOam7qIG\\\/Ml4S8BMYoFZSvdpX9+hXJ61JdWaIfFhlwcgqOricf99TaXS5\\\/BOup4Xy0bAS85B5i1uJs3wuogbXbEaMTGUw4vQJxj3muTLTnspIFJj1uHbyikGriit2yxKHslWkqHD+LuBEqK\",\"encryptionName\":\"AES_GCM\",\"privateKeySha256\":\"45cb7cb283d0b9ca64219bd0bc033c0fad461aaf6783d5be71eac2e772c3c828\"}",
            "updatedAt" : "2021-03-19T12:21:03Z",
            "type" : "my_remote_object",
            "checksum" : "dbc369736dade41722b7005db5efae1fb99aca7aae9417b6184eaf423e2d860b",
            "createdAt" : "2021-03-19T12:21:03Z"
          },
          "privateKey" : "j6tifPZTjUtGoz+1RJkO8dOMlu48MUUSlwACw\/fCBw0="
        }
      },
      "url" : "https:\/\/api.beamapp.co\/graphql",
      "headers" : {
        "Accept-Language" : "en",
        "Content-Type" : "application\/json",
        "User-Agent" : "Beam client, 0.1.0 (1)",
        "Authorization" : "Bearer eyJhbGciOiJIUzI1NiJ9.eyJqdGkiOiJmZWNkMTFkMy0yZDZmLTQ3OTgtYTM4YS1lMjkzN2JmZGZmNjIiLCJzdWIiOiJlMTQwYzU5YS1lYmIyLTQ3YjEtYmU3OC05ZDJkNTYyNWRjYWQiLCJzY3AiOiJ1c2VyIiwiYXVkIjpudWxsLCJpYXQiOjE2MjgwODk0NzgsImV4cCI6MTYzMDcxOTIyNH0.9b3qmS4IWHbQ1R2nQ_YLe_s58bMP_iegQXcLAJC7w-I",
        "Accept" : "application\/json"
      }
    }
  },
  {
    "request" : {
      "url" : "https:\/\/api.beamapp.co\/graphql",
      "body" : {
        "query" : "mutation UpdateBeamObject($beamObject: BeamObjectInput!, $privateKey: String) {\n  updateBeamObject(input: {beamObject: $beamObject, privateKey: $privateKey}) {\n    beamObject {\n      id\n      checksum\n      type\n    }\n    errors {\n      objectid\n      path\n      message\n    }\n  }\n}\n",
        "variables" : {
          "beamObject" : {
            "id" : "395D94E1-E0DF-4ECA-93E6-8778984BCD58",
            "data" : "{\"data\":\"jUlV4EKvnNW97gdv6OsIb1bq71JLc3k8Er7TkoOqCCGKNGM7IGiOJGQnHGU6Rxqyn+hGuAhaROmslcd+nb1wF9mdQ3GP6NxVlBiCl4z34eZGGZDkdcrEwGH62X2Z7s9U8bKtl70JsdE8Js6w\\\/fA7yAvY1SP2WbJJ\",\"encryptionName\":\"AES_GCM\",\"privateKeySha256\":\"45cb7cb283d0b9ca64219bd0bc033c0fad461aaf6783d5be71eac2e772c3c828\"}",
            "updatedAt" : "2021-03-19T12:21:03Z",
            "type" : "my_remote_object",
            "checksum" : "fe147aac80e027967f9dae92fc5d272bd0c06519b18f7b27d1aa7feb2a4e3d3f",
            "createdAt" : "2021-03-19T12:21:03Z"
          },
          "privateKey" : "j6tifPZTjUtGoz+1RJkO8dOMlu48MUUSlwACw\/fCBw0="
        }
      },
      "method" : "POST",
      "headers" : {
        "Authorization" : "Bearer eyJhbGciOiJIUzI1NiJ9.eyJqdGkiOiJmZWNkMTFkMy0yZDZmLTQ3OTgtYTM4YS1lMjkzN2JmZGZmNjIiLCJzdWIiOiJlMTQwYzU5YS1lYmIyLTQ3YjEtYmU3OC05ZDJkNTYyNWRjYWQiLCJzY3AiOiJ1c2VyIiwiYXVkIjpudWxsLCJpYXQiOjE2MjgwODk0NzgsImV4cCI6MTYzMDcxOTIyNH0.9b3qmS4IWHbQ1R2nQ_YLe_s58bMP_iegQXcLAJC7w-I",
        "User-Agent" : "Beam client, 0.1.0 (1)",
        "Accept" : "application\/json",
        "Accept-Language" : "en",
        "Content-Type" : "application\/json"
      }
    },
    "response" : {
      "url" : "https:\/\/api.beamapp.co\/graphql",
      "status" : 200,
      "headers" : {
        "Date" : "Wed, 04 Aug 2021 15:04:37 GMT",
        "Connection" : "keep-alive",
        "Strict-Transport-Security" : "max-age=63072000; includeSubDomains",
        "X-Xss-Protection" : "1; mode=block",
        "Transfer-Encoding" : "Identity",
        "X-Content-Type-Options" : "nosniff",
        "Vary" : "Accept, Origin",
        "X-Permitted-Cross-Domain-Policies" : "none",
        "X-Runtime" : "0.027807",
        "Cache-Control" : "max-age=0, private, must-revalidate",
        "X-Frame-Options" : "SAMEORIGIN",
        "X-Request-Id" : "11aa8807-810b-41bd-9ab7-d6a896901bee",
        "Via" : "1.1 vegur",
        "Server" : "Cowboy",
        "Content-Type" : "application\/json; charset=utf-8",
        "Referrer-Policy" : "strict-origin-when-cross-origin",
        "Etag" : "W\/\"cd5231149cee0fb2dc2c1125957f91a8\"",
        "X-Download-Options" : "noopen"
      },
      "body" : {
        "data" : {
          "updateBeamObject" : {
            "beamObject" : {
              "id" : "395d94e1-e0df-4eca-93e6-8778984bcd58",
              "checksum" : "fe147aac80e027967f9dae92fc5d272bd0c06519b18f7b27d1aa7feb2a4e3d3f",
              "type" : "my_remote_object"
            },
            "errors" : [

            ]
          }
        }
      }
    }
  },
  {
    "request" : {
      "body" : {
        "query" : "mutation UpdateBeamObjects($beamObjects: [BeamObjectInput!]!, $privateKey: String) {\n  updateBeamObjects(input: {beamObjectsInput: $beamObjects, privateKey: $privateKey}) {\n    beamObjects {\n      id\n      checksum\n      type\n    }\n    errors {\n      objectid\n      path\n      message\n    }\n  }\n}\n",
        "variables" : {
          "privateKey" : "j6tifPZTjUtGoz+1RJkO8dOMlu48MUUSlwACw\/fCBw0=",
          "beamObjects" : [
            {
              "id" : "195D94E1-E0DF-4ECA-93E6-8778984BCD58",
              "data" : "{\"data\":\"pamw6QgDDkMtaeCidJDr7ASdT9gn1LEL0ZMPPxLBu74Kuou2bUt9GCX0N7S48xyLOXqfNOlgZ4urznXL115l5XXwnS8wMznriFVlkB8Aj1A23kawcO9MiZ8wEzP9xK3BOjpdHa\\\/MRexSvm1ZtKJlOhpnNc9ew14T1WY=\",\"encryptionName\":\"AES_GCM\",\"privateKeySha256\":\"45cb7cb283d0b9ca64219bd0bc033c0fad461aaf6783d5be71eac2e772c3c828\"}",
              "checksum" : "6bd6950a479d12bbd7ca9824b570b15510803b24f0667b275a6c9be7b46ab0b9",
              "previousChecksum" : "00a3c318664ebae8b2239cd2be6dae3f546feb789cb005fa9f31512709f2fb00",
              "updatedAt" : "2021-03-19T12:21:03Z",
              "type" : "my_remote_object",
              "createdAt" : "2021-03-19T12:21:03Z"
            },
            {
              "id" : "295D94E1-E0DF-4ECA-93E6-8778984BCD58",
              "data" : "{\"data\":\"Jgfp8nc67g3+KHdyKqvJJqGxROb2qihL3XcuRGClM6ydI7KmoAA7DpFhgXyqZCHpScziR\\\/9KAsL6r7pLxbHP6NbxWMdRnolrvA3+AckhorUJ6sMnSUJ1alqMAapwk6oIfOasA+zJI0333fRZ+iQR\\\/+r\\\/Zq7e9GT036s=\",\"encryptionName\":\"AES_GCM\",\"privateKeySha256\":\"45cb7cb283d0b9ca64219bd0bc033c0fad461aaf6783d5be71eac2e772c3c828\"}",
              "checksum" : "30be1cf47851e3baa34f1c06b2ded0f683e84284962b46bcd1a8a166449c9c8c",
              "previousChecksum" : "11a3c318664ebae8b2239cd2be6dae3f546feb789cb005fa9f31512709f2fb11",
              "updatedAt" : "2021-03-19T12:21:03Z",
              "type" : "my_remote_object",
              "createdAt" : "2021-03-19T12:21:03Z"
            },
            {
              "id" : "395D94E1-E0DF-4ECA-93E6-8778984BCD58",
              "data" : "{\"data\":\"nwq55Va+LnRw0VFfVJa4bUGSnM9Gedul0O+hPvKAhWwcTeNU8pSl5JXdoT1COGA\\\/trsZjetuLD8LK6yGVCxVRwnB0d5\\\/WGBqE9R9VMgj\\\/XjK2Rj99nWi2aSLazjYPw3UKjrP9YBvMUFRpNrCG2Cconj70qxKSfAG\",\"encryptionName\":\"AES_GCM\",\"privateKeySha256\":\"45cb7cb283d0b9ca64219bd0bc033c0fad461aaf6783d5be71eac2e772c3c828\"}",
              "checksum" : "fe147aac80e027967f9dae92fc5d272bd0c06519b18f7b27d1aa7feb2a4e3d3f",
              "previousChecksum" : "fe147aac80e027967f9dae92fc5d272bd0c06519b18f7b27d1aa7feb2a4e3d3f",
              "updatedAt" : "2021-03-19T12:21:03Z",
              "type" : "my_remote_object",
              "createdAt" : "2021-03-19T12:21:03Z"
            }
          ]
        }
      },
      "method" : "POST",
      "headers" : {
        "Accept-Language" : "en",
        "Authorization" : "Bearer eyJhbGciOiJIUzI1NiJ9.eyJqdGkiOiJmZWNkMTFkMy0yZDZmLTQ3OTgtYTM4YS1lMjkzN2JmZGZmNjIiLCJzdWIiOiJlMTQwYzU5YS1lYmIyLTQ3YjEtYmU3OC05ZDJkNTYyNWRjYWQiLCJzY3AiOiJ1c2VyIiwiYXVkIjpudWxsLCJpYXQiOjE2MjgwODk0NzgsImV4cCI6MTYzMDcxOTIyNH0.9b3qmS4IWHbQ1R2nQ_YLe_s58bMP_iegQXcLAJC7w-I",
        "Content-Type" : "application\/json",
        "Accept" : "application\/json",
        "User-Agent" : "Beam client, 0.1.0 (1)"
      },
      "url" : "https:\/\/api.beamapp.co\/graphql"
    },
    "response" : {
      "status" : 200,
      "headers" : {
        "X-Xss-Protection" : "1; mode=block",
        "Server" : "Cowboy",
        "X-Frame-Options" : "SAMEORIGIN",
        "Etag" : "W\/\"497f8d347c15491cfc149492fec4df84\"",
        "Via" : "1.1 vegur",
        "Connection" : "keep-alive",
        "X-Request-Id" : "fe3d7a12-34b5-4baf-8d1d-9f01691cb100",
        "Content-Type" : "application\/json; charset=utf-8",
        "Date" : "Wed, 04 Aug 2021 15:04:37 GMT",
        "Transfer-Encoding" : "Identity",
        "Vary" : "Accept, Origin",
        "X-Content-Type-Options" : "nosniff",
        "X-Download-Options" : "noopen",
        "Referrer-Policy" : "strict-origin-when-cross-origin",
        "Cache-Control" : "max-age=0, private, must-revalidate",
        "Strict-Transport-Security" : "max-age=63072000; includeSubDomains",
        "X-Runtime" : "0.035482",
        "X-Permitted-Cross-Domain-Policies" : "none"
      },
      "url" : "https:\/\/api.beamapp.co\/graphql",
      "body" : {
        "data" : {
          "updateBeamObjects" : {
            "errors" : [
              {
                "path" : [
                  "attributes",
                  "previous_checksum"
                ],
                "objectid" : "195d94e1-e0df-4eca-93e6-8778984bcd58",
                "message" : "Differs from current checksum"
              },
              {
                "path" : [
                  "attributes",
                  "previous_checksum"
                ],
                "objectid" : "295d94e1-e0df-4eca-93e6-8778984bcd58",
                "message" : "Differs from current checksum"
              }
            ],
            "beamObjects" : [
              {
                "id" : "395d94e1-e0df-4eca-93e6-8778984bcd58",
                "checksum" : "fe147aac80e027967f9dae92fc5d272bd0c06519b18f7b27d1aa7feb2a4e3d3f",
                "type" : "my_remote_object"
              }
            ]
          }
        }
      }
    }
  },
  {
    "response" : {
      "body" : {
        "data" : {
          "beamObject" : {
            "id" : "195d94e1-e0df-4eca-93e6-8778984bcd58",
            "data" : "{\"data\":\"RdFjSZMkQh0yDja9mtlnUAwn3X2kWBKybvvDX01imisAkEHtAldrWYoIIWn2RI6eXjHWdturL9\\\/4EcSZPN5cqda2c1I20KxW\\\/kmT4dURvWJsr4L4x\\\/+4B94RD4eZjzSTRBSMbz3xfGOrddrfLef4ppSXoMybN6Hl\",\"encryptionName\":\"AES_GCM\",\"privateKeySha256\":\"45cb7cb283d0b9ca64219bd0bc033c0fad461aaf6783d5be71eac2e772c3c828\"}",
            "checksum" : "1329717e2a5c440af3e94efeecba3bee495963998506bb662c0ab2da0cd459e6",
            "deletedAt" : null,
            "updatedAt" : "2021-03-19T12:21:03Z",
            "type" : "my_remote_object",
            "createdAt" : "2021-03-19T12:21:03Z"
          }
        }
      },
      "headers" : {
        "Date" : "Wed, 04 Aug 2021 15:04:38 GMT",
        "X-Download-Options" : "noopen",
        "Server" : "Cowboy",
        "X-Xss-Protection" : "1; mode=block",
        "X-Request-Id" : "a242c07d-01d0-4022-82db-d7c61d59cdc7",
        "Vary" : "Accept, Origin",
        "X-Runtime" : "0.016777",
        "Strict-Transport-Security" : "max-age=63072000; includeSubDomains",
        "Referrer-Policy" : "strict-origin-when-cross-origin",
        "Transfer-Encoding" : "Identity",
        "Via" : "1.1 vegur",
        "Content-Type" : "application\/json; charset=utf-8",
        "X-Permitted-Cross-Domain-Policies" : "none",
        "X-Frame-Options" : "SAMEORIGIN",
        "Etag" : "W\/\"9d4f230b6c23125dd9d03c0c4ec625da\"",
        "Cache-Control" : "max-age=0, private, must-revalidate",
        "X-Content-Type-Options" : "nosniff",
        "Connection" : "keep-alive"
      },
      "url" : "https:\/\/api.beamapp.co\/graphql",
      "status" : 200
    },
    "request" : {
      "body" : {
        "query" : "query beamObject($id: ID!) {\n  beamObject(id: $id) {\n    id\n    data\n    checksum\n    type\n    createdAt\n    updatedAt\n    deletedAt\n  }\n}\n",
        "variables" : {
          "id" : "195D94E1-E0DF-4ECA-93E6-8778984BCD58"
        }
      },
      "headers" : {
        "Content-Type" : "application\/json",
        "Authorization" : "Bearer eyJhbGciOiJIUzI1NiJ9.eyJqdGkiOiJmZWNkMTFkMy0yZDZmLTQ3OTgtYTM4YS1lMjkzN2JmZGZmNjIiLCJzdWIiOiJlMTQwYzU5YS1lYmIyLTQ3YjEtYmU3OC05ZDJkNTYyNWRjYWQiLCJzY3AiOiJ1c2VyIiwiYXVkIjpudWxsLCJpYXQiOjE2MjgwODk0NzgsImV4cCI6MTYzMDcxOTIyNH0.9b3qmS4IWHbQ1R2nQ_YLe_s58bMP_iegQXcLAJC7w-I",
        "Accept-Language" : "en",
        "Accept" : "application\/json",
        "User-Agent" : "Beam client, 0.1.0 (1)"
      },
      "method" : "POST",
      "url" : "https:\/\/api.beamapp.co\/graphql"
    }
  },
  {
    "request" : {
      "headers" : {
        "Content-Type" : "application\/json",
        "Authorization" : "Bearer eyJhbGciOiJIUzI1NiJ9.eyJqdGkiOiJmZWNkMTFkMy0yZDZmLTQ3OTgtYTM4YS1lMjkzN2JmZGZmNjIiLCJzdWIiOiJlMTQwYzU5YS1lYmIyLTQ3YjEtYmU3OC05ZDJkNTYyNWRjYWQiLCJzY3AiOiJ1c2VyIiwiYXVkIjpudWxsLCJpYXQiOjE2MjgwODk0NzgsImV4cCI6MTYzMDcxOTIyNH0.9b3qmS4IWHbQ1R2nQ_YLe_s58bMP_iegQXcLAJC7w-I",
        "Accept-Language" : "en",
        "Accept" : "application\/json",
        "User-Agent" : "Beam client, 0.1.0 (1)"
      },
      "method" : "POST",
      "body" : {
        "query" : "query beamObject($id: ID!) {\n  beamObject(id: $id) {\n    id\n    data\n    checksum\n    type\n    createdAt\n    updatedAt\n    deletedAt\n  }\n}\n",
        "variables" : {
          "id" : "295D94E1-E0DF-4ECA-93E6-8778984BCD58"
        }
      },
      "url" : "https:\/\/api.beamapp.co\/graphql"
    },
    "response" : {
      "url" : "https:\/\/api.beamapp.co\/graphql",
      "body" : {
        "data" : {
          "beamObject" : {
            "id" : "295d94e1-e0df-4eca-93e6-8778984bcd58",
            "data" : "{\"data\":\"KqBQuzKH9gq+ahGqrsOam7qIG\\\/Ml4S8BMYoFZSvdpX9+hXJ61JdWaIfFhlwcgqOricf99TaXS5\\\/BOup4Xy0bAS85B5i1uJs3wuogbXbEaMTGUw4vQJxj3muTLTnspIFJj1uHbyikGriit2yxKHslWkqHD+LuBEqK\",\"encryptionName\":\"AES_GCM\",\"privateKeySha256\":\"45cb7cb283d0b9ca64219bd0bc033c0fad461aaf6783d5be71eac2e772c3c828\"}",
            "checksum" : "dbc369736dade41722b7005db5efae1fb99aca7aae9417b6184eaf423e2d860b",
            "deletedAt" : null,
            "updatedAt" : "2021-03-19T12:21:03Z",
            "type" : "my_remote_object",
            "createdAt" : "2021-03-19T12:21:03Z"
          }
        }
      },
      "headers" : {
        "X-Runtime" : "0.017825",
        "X-Frame-Options" : "SAMEORIGIN",
        "Content-Type" : "application\/json; charset=utf-8",
        "X-Permitted-Cross-Domain-Policies" : "none",
        "X-Content-Type-Options" : "nosniff",
        "Referrer-Policy" : "strict-origin-when-cross-origin",
        "Transfer-Encoding" : "Identity",
        "Etag" : "W\/\"a305e089ace5703bb5b8fbe30cfee7c3\"",
        "X-Xss-Protection" : "1; mode=block",
        "X-Request-Id" : "e05dc737-2b27-4231-a06a-e2b48551823c",
        "Date" : "Wed, 04 Aug 2021 15:04:38 GMT",
        "Vary" : "Accept, Origin",
        "X-Download-Options" : "noopen",
        "Via" : "1.1 vegur",
        "Cache-Control" : "max-age=0, private, must-revalidate",
        "Strict-Transport-Security" : "max-age=63072000; includeSubDomains",
        "Server" : "Cowboy",
        "Connection" : "keep-alive"
      },
      "status" : 200
    }
  },
  {
    "request" : {
      "method" : "POST",
      "headers" : {
        "Accept-Language" : "en",
        "Accept" : "application\/json",
        "Authorization" : "Bearer eyJhbGciOiJIUzI1NiJ9.eyJqdGkiOiJmZWNkMTFkMy0yZDZmLTQ3OTgtYTM4YS1lMjkzN2JmZGZmNjIiLCJzdWIiOiJlMTQwYzU5YS1lYmIyLTQ3YjEtYmU3OC05ZDJkNTYyNWRjYWQiLCJzY3AiOiJ1c2VyIiwiYXVkIjpudWxsLCJpYXQiOjE2MjgwODk0NzgsImV4cCI6MTYzMDcxOTIyNH0.9b3qmS4IWHbQ1R2nQ_YLe_s58bMP_iegQXcLAJC7w-I",
        "Content-Type" : "application\/json",
        "User-Agent" : "Beam client, 0.1.0 (1)"
      },
      "body" : {
        "query" : "mutation UpdateBeamObjects($beamObjects: [BeamObjectInput!]!, $privateKey: String) {\n  updateBeamObjects(input: {beamObjectsInput: $beamObjects, privateKey: $privateKey}) {\n    beamObjects {\n      id\n      checksum\n      type\n    }\n    errors {\n      objectid\n      path\n      message\n    }\n  }\n}\n",
        "variables" : {
          "privateKey" : "j6tifPZTjUtGoz+1RJkO8dOMlu48MUUSlwACw\/fCBw0=",
          "beamObjects" : [
            {
              "id" : "195D94E1-E0DF-4ECA-93E6-8778984BCD58",
              "data" : "{\"data\":\"6feKK6aIsC6GzWyOiQquqDRfdgCNLzg2LVKcojeZWcM2fc5Vv\\\/nLyQAG2vpb8PCSSFEKF460SXCFG20OodD\\\/XCY36XuEGSD0CKoENOLuTEOcfky5a7FF8h4b3NDJTSp9oBtcWVfSlip\\\/C74DNig5b4eYS4ehuGvW5q8wJh0KZ4OfwnHgtEgEh4MY\",\"encryptionName\":\"AES_GCM\",\"privateKeySha256\":\"45cb7cb283d0b9ca64219bd0bc033c0fad461aaf6783d5be71eac2e772c3c828\"}",
              "checksum" : "f4cd6499ffbd657bd7649afb6ba8a7777c7fd225fe906d471edd60bff246f595",
              "previousChecksum" : "1329717e2a5c440af3e94efeecba3bee495963998506bb662c0ab2da0cd459e6",
              "updatedAt" : "2021-03-19T12:21:03Z",
              "type" : "my_remote_object",
              "createdAt" : "2021-03-19T12:21:03Z"
            },
            {
              "id" : "295D94E1-E0DF-4ECA-93E6-8778984BCD58",
              "data" : "{\"data\":\"rUJzlwys5oY2WXukrc654PY+DItZ0qVok2QnuSvR+Ud9SKjMCGRRORrupS3P5jRTVQdpA91wnMhUvIgrO2ZZgIgJT4q5CWmk7wPZraZFM31lLRK0KCjziCbCqSVdfecKWPOtPURnG5xCu0n9nzkoN1gpT\\\/\\\/XIF0oN9URKOO1gBk8MtyZycmBlDae\",\"encryptionName\":\"AES_GCM\",\"privateKeySha256\":\"45cb7cb283d0b9ca64219bd0bc033c0fad461aaf6783d5be71eac2e772c3c828\"}",
              "checksum" : "c74c22e7ebcb927ca666ff2ec5b9ab68ab6bd19c6f4a735236de58004d646230",
              "previousChecksum" : "dbc369736dade41722b7005db5efae1fb99aca7aae9417b6184eaf423e2d860b",
              "updatedAt" : "2021-03-19T12:21:03Z",
              "type" : "my_remote_object",
              "createdAt" : "2021-03-19T12:21:03Z"
            }
          ]
        }
      },
      "url" : "https:\/\/api.beamapp.co\/graphql"
    },
    "response" : {
      "status" : 200,
      "headers" : {
        "Server" : "Cowboy",
        "Date" : "Wed, 04 Aug 2021 15:04:38 GMT",
        "Transfer-Encoding" : "Identity",
        "Referrer-Policy" : "strict-origin-when-cross-origin",
        "X-Request-Id" : "e57113b4-8e8a-470a-b4a6-f3438416152c",
        "Connection" : "keep-alive",
        "Cache-Control" : "max-age=0, private, must-revalidate",
        "Etag" : "W\/\"66fea39f380727afce42676c8d4090f1\"",
        "X-Xss-Protection" : "1; mode=block",
        "X-Runtime" : "0.035560",
        "X-Frame-Options" : "SAMEORIGIN",
        "Vary" : "Accept, Origin",
        "Content-Type" : "application\/json; charset=utf-8",
        "Via" : "1.1 vegur",
        "X-Content-Type-Options" : "nosniff",
        "X-Download-Options" : "noopen",
        "X-Permitted-Cross-Domain-Policies" : "none",
        "Strict-Transport-Security" : "max-age=63072000; includeSubDomains"
      },
      "url" : "https:\/\/api.beamapp.co\/graphql",
      "body" : {
        "data" : {
          "updateBeamObjects" : {
            "errors" : [

            ],
            "beamObjects" : [
              {
                "id" : "195d94e1-e0df-4eca-93e6-8778984bcd58",
                "checksum" : "f4cd6499ffbd657bd7649afb6ba8a7777c7fd225fe906d471edd60bff246f595",
                "type" : "my_remote_object"
              },
              {
                "id" : "295d94e1-e0df-4eca-93e6-8778984bcd58",
                "checksum" : "c74c22e7ebcb927ca666ff2ec5b9ab68ab6bd19c6f4a735236de58004d646230",
                "type" : "my_remote_object"
              }
            ]
          }
        }
      }
    }
  },
  {
    "request" : {
      "method" : "POST",
      "url" : "https:\/\/api.beamapp.co\/graphql",
      "headers" : {
        "Accept-Language" : "en",
        "User-Agent" : "Beam client, 0.1.0 (1)",
        "Authorization" : "Bearer eyJhbGciOiJIUzI1NiJ9.eyJqdGkiOiJmZWNkMTFkMy0yZDZmLTQ3OTgtYTM4YS1lMjkzN2JmZGZmNjIiLCJzdWIiOiJlMTQwYzU5YS1lYmIyLTQ3YjEtYmU3OC05ZDJkNTYyNWRjYWQiLCJzY3AiOiJ1c2VyIiwiYXVkIjpudWxsLCJpYXQiOjE2MjgwODk0NzgsImV4cCI6MTYzMDcxOTIyNH0.9b3qmS4IWHbQ1R2nQ_YLe_s58bMP_iegQXcLAJC7w-I",
        "Content-Type" : "application\/json",
        "Accept" : "application\/json"
      },
      "body" : {
        "query" : "query beamObject($id: ID!) {\n  beamObject(id: $id) {\n    id\n    data\n    checksum\n    type\n    createdAt\n    updatedAt\n    deletedAt\n  }\n}\n",
        "variables" : {
          "id" : "195D94E1-E0DF-4ECA-93E6-8778984BCD58"
        }
      }
    },
    "response" : {
      "headers" : {
        "X-Download-Options" : "noopen",
        "Vary" : "Accept, Origin",
        "Via" : "1.1 vegur",
        "X-Permitted-Cross-Domain-Policies" : "none",
        "X-Frame-Options" : "SAMEORIGIN",
        "X-Content-Type-Options" : "nosniff",
        "Date" : "Wed, 04 Aug 2021 15:04:38 GMT",
        "Connection" : "keep-alive",
        "Strict-Transport-Security" : "max-age=63072000; includeSubDomains",
        "Cache-Control" : "max-age=0, private, must-revalidate",
        "X-Runtime" : "0.013880",
        "Server" : "Cowboy",
        "Transfer-Encoding" : "Identity",
        "Referrer-Policy" : "strict-origin-when-cross-origin",
        "X-Request-Id" : "e82cf320-38ef-449d-9103-ffa87c225551",
        "Content-Type" : "application\/json; charset=utf-8",
        "X-Xss-Protection" : "1; mode=block",
        "Etag" : "W\/\"075a0f3f43171ca79b9c2a1e099228a8\""
      },
      "status" : 200,
      "url" : "https:\/\/api.beamapp.co\/graphql",
      "body" : {
        "data" : {
          "beamObject" : {
            "id" : "195d94e1-e0df-4eca-93e6-8778984bcd58",
            "data" : "{\"data\":\"6feKK6aIsC6GzWyOiQquqDRfdgCNLzg2LVKcojeZWcM2fc5Vv\\\/nLyQAG2vpb8PCSSFEKF460SXCFG20OodD\\\/XCY36XuEGSD0CKoENOLuTEOcfky5a7FF8h4b3NDJTSp9oBtcWVfSlip\\\/C74DNig5b4eYS4ehuGvW5q8wJh0KZ4OfwnHgtEgEh4MY\",\"encryptionName\":\"AES_GCM\",\"privateKeySha256\":\"45cb7cb283d0b9ca64219bd0bc033c0fad461aaf6783d5be71eac2e772c3c828\"}",
            "checksum" : "f4cd6499ffbd657bd7649afb6ba8a7777c7fd225fe906d471edd60bff246f595",
            "deletedAt" : null,
            "updatedAt" : "2021-03-19T12:21:03Z",
            "type" : "my_remote_object",
            "createdAt" : "2021-03-19T12:21:03Z"
          }
        }
      }
    }
  },
  {
    "response" : {
      "status" : 200,
      "headers" : {
        "Server" : "Cowboy",
        "X-Download-Options" : "noopen",
        "Connection" : "keep-alive",
        "Etag" : "W\/\"de5446113ba80ee889466e04d114e4fd\"",
        "Strict-Transport-Security" : "max-age=63072000; includeSubDomains",
        "X-Request-Id" : "f1a4fb5a-faed-4d80-bb4e-2e1c53056ce9",
        "Referrer-Policy" : "strict-origin-when-cross-origin",
        "X-Permitted-Cross-Domain-Policies" : "none",
        "X-Runtime" : "0.012026",
        "Date" : "Wed, 04 Aug 2021 15:04:38 GMT",
        "X-Xss-Protection" : "1; mode=block",
        "Cache-Control" : "max-age=0, private, must-revalidate",
        "Content-Type" : "application\/json; charset=utf-8",
        "Vary" : "Accept, Origin",
        "Via" : "1.1 vegur",
        "X-Frame-Options" : "SAMEORIGIN",
        "Transfer-Encoding" : "Identity",
        "X-Content-Type-Options" : "nosniff"
      },
      "body" : {
        "data" : {
          "beamObject" : {
            "id" : "295d94e1-e0df-4eca-93e6-8778984bcd58",
            "data" : "{\"data\":\"rUJzlwys5oY2WXukrc654PY+DItZ0qVok2QnuSvR+Ud9SKjMCGRRORrupS3P5jRTVQdpA91wnMhUvIgrO2ZZgIgJT4q5CWmk7wPZraZFM31lLRK0KCjziCbCqSVdfecKWPOtPURnG5xCu0n9nzkoN1gpT\\\/\\\/XIF0oN9URKOO1gBk8MtyZycmBlDae\",\"encryptionName\":\"AES_GCM\",\"privateKeySha256\":\"45cb7cb283d0b9ca64219bd0bc033c0fad461aaf6783d5be71eac2e772c3c828\"}",
            "checksum" : "c74c22e7ebcb927ca666ff2ec5b9ab68ab6bd19c6f4a735236de58004d646230",
            "deletedAt" : null,
            "updatedAt" : "2021-03-19T12:21:03Z",
            "type" : "my_remote_object",
            "createdAt" : "2021-03-19T12:21:03Z"
          }
        }
      },
      "url" : "https:\/\/api.beamapp.co\/graphql"
    },
    "request" : {
      "headers" : {
        "Accept-Language" : "en",
        "User-Agent" : "Beam client, 0.1.0 (1)",
        "Accept" : "application\/json",
        "Content-Type" : "application\/json",
        "Authorization" : "Bearer eyJhbGciOiJIUzI1NiJ9.eyJqdGkiOiJmZWNkMTFkMy0yZDZmLTQ3OTgtYTM4YS1lMjkzN2JmZGZmNjIiLCJzdWIiOiJlMTQwYzU5YS1lYmIyLTQ3YjEtYmU3OC05ZDJkNTYyNWRjYWQiLCJzY3AiOiJ1c2VyIiwiYXVkIjpudWxsLCJpYXQiOjE2MjgwODk0NzgsImV4cCI6MTYzMDcxOTIyNH0.9b3qmS4IWHbQ1R2nQ_YLe_s58bMP_iegQXcLAJC7w-I"
      },
      "url" : "https:\/\/api.beamapp.co\/graphql",
      "body" : {
        "query" : "query beamObject($id: ID!) {\n  beamObject(id: $id) {\n    id\n    data\n    checksum\n    type\n    createdAt\n    updatedAt\n    deletedAt\n  }\n}\n",
        "variables" : {
          "id" : "295D94E1-E0DF-4ECA-93E6-8778984BCD58"
        }
      },
      "method" : "POST"
    }
  },
  {
    "request" : {
      "method" : "POST",
      "body" : {
        "query" : "query beamObject($id: ID!) {\n  beamObject(id: $id) {\n    id\n    data\n    checksum\n    type\n    createdAt\n    updatedAt\n    deletedAt\n  }\n}\n",
        "variables" : {
          "id" : "395D94E1-E0DF-4ECA-93E6-8778984BCD58"
        }
      },
      "url" : "https:\/\/api.beamapp.co\/graphql",
      "headers" : {
        "User-Agent" : "Beam client, 0.1.0 (1)",
        "Accept-Language" : "en",
        "Authorization" : "Bearer eyJhbGciOiJIUzI1NiJ9.eyJqdGkiOiJmZWNkMTFkMy0yZDZmLTQ3OTgtYTM4YS1lMjkzN2JmZGZmNjIiLCJzdWIiOiJlMTQwYzU5YS1lYmIyLTQ3YjEtYmU3OC05ZDJkNTYyNWRjYWQiLCJzY3AiOiJ1c2VyIiwiYXVkIjpudWxsLCJpYXQiOjE2MjgwODk0NzgsImV4cCI6MTYzMDcxOTIyNH0.9b3qmS4IWHbQ1R2nQ_YLe_s58bMP_iegQXcLAJC7w-I",
        "Accept" : "application\/json",
        "Content-Type" : "application\/json"
      }
    },
    "response" : {
      "status" : 200,
      "url" : "https:\/\/api.beamapp.co\/graphql",
      "headers" : {
        "Server" : "Cowboy",
        "Etag" : "W\/\"001d783160f4fd3ec22fc8afbadf9254\"",
        "X-Runtime" : "0.010425",
        "X-Download-Options" : "noopen",
        "Vary" : "Accept, Origin",
        "Connection" : "keep-alive",
        "X-Permitted-Cross-Domain-Policies" : "none",
        "Referrer-Policy" : "strict-origin-when-cross-origin",
        "X-Content-Type-Options" : "nosniff",
        "Transfer-Encoding" : "Identity",
        "Strict-Transport-Security" : "max-age=63072000; includeSubDomains",
        "Cache-Control" : "max-age=0, private, must-revalidate",
        "Content-Type" : "application\/json; charset=utf-8",
        "X-Xss-Protection" : "1; mode=block",
        "Via" : "1.1 vegur",
        "X-Request-Id" : "e76cae5e-7abb-46a8-a4cb-1ec9f33ef05c",
        "X-Frame-Options" : "SAMEORIGIN",
        "Date" : "Wed, 04 Aug 2021 15:04:38 GMT"
      },
      "body" : {
        "data" : {
          "beamObject" : {
            "id" : "395d94e1-e0df-4eca-93e6-8778984bcd58",
            "data" : "{\"data\":\"nwq55Va+LnRw0VFfVJa4bUGSnM9Gedul0O+hPvKAhWwcTeNU8pSl5JXdoT1COGA\\\/trsZjetuLD8LK6yGVCxVRwnB0d5\\\/WGBqE9R9VMgj\\\/XjK2Rj99nWi2aSLazjYPw3UKjrP9YBvMUFRpNrCG2Cconj70qxKSfAG\",\"encryptionName\":\"AES_GCM\",\"privateKeySha256\":\"45cb7cb283d0b9ca64219bd0bc033c0fad461aaf6783d5be71eac2e772c3c828\"}",
            "checksum" : "fe147aac80e027967f9dae92fc5d272bd0c06519b18f7b27d1aa7feb2a4e3d3f",
            "deletedAt" : null,
            "updatedAt" : "2021-03-19T12:21:03Z",
            "type" : "my_remote_object",
            "createdAt" : "2021-03-19T12:21:03Z"
          }
        }
      }
    }
  },
  {
    "request" : {
      "headers" : {
        "Accept" : "application\/json",
        "Accept-Language" : "en",
        "Authorization" : "Bearer eyJhbGciOiJIUzI1NiJ9.eyJqdGkiOiJmZWNkMTFkMy0yZDZmLTQ3OTgtYTM4YS1lMjkzN2JmZGZmNjIiLCJzdWIiOiJlMTQwYzU5YS1lYmIyLTQ3YjEtYmU3OC05ZDJkNTYyNWRjYWQiLCJzY3AiOiJ1c2VyIiwiYXVkIjpudWxsLCJpYXQiOjE2MjgwODk0NzgsImV4cCI6MTYzMDcxOTIyNH0.9b3qmS4IWHbQ1R2nQ_YLe_s58bMP_iegQXcLAJC7w-I",
        "User-Agent" : "Beam client, 0.1.0 (1)",
        "Content-Type" : "application\/json"
      },
      "method" : "POST",
      "url" : "https:\/\/api.beamapp.co\/graphql",
      "body" : {
        "query" : "mutation DeleteAllBeamObjects {\n  deleteAllBeamObjects(input: {}) {\n    success\n    errors {\n      path\n      message\n    }\n  }\n}\n",
        "variables" : {

        }
      }
    },
    "response" : {
      "headers" : {
        "Transfer-Encoding" : "Identity",
        "Server" : "Cowboy",
        "Strict-Transport-Security" : "max-age=63072000; includeSubDomains",
        "X-Request-Id" : "157796f9-6d3f-4357-9889-2aa67c8bffcd",
        "Connection" : "keep-alive",
        "Etag" : "W\/\"4979b027853222033b78668c613a2e60\"",
        "Date" : "Wed, 04 Aug 2021 15:04:38 GMT",
        "X-Runtime" : "0.011400",
        "Vary" : "Accept, Origin",
        "Via" : "1.1 vegur",
        "Cache-Control" : "max-age=0, private, must-revalidate",
        "X-Permitted-Cross-Domain-Policies" : "none",
        "X-Content-Type-Options" : "nosniff",
        "X-Frame-Options" : "SAMEORIGIN",
        "Referrer-Policy" : "strict-origin-when-cross-origin",
        "Content-Type" : "application\/json; charset=utf-8",
        "X-Download-Options" : "noopen",
        "X-Xss-Protection" : "1; mode=block"
      },
      "status" : 200,
      "body" : {
        "data" : {
          "deleteAllBeamObjects" : {
            "success" : true,
            "errors" : [

            ]
          }
        }
      },
      "url" : "https:\/\/api.beamapp.co\/graphql"
    }
  }
]